Workbook

Sheet Inputs
A1: Wong Family model — INPUTS
A2: Blue = hardcoded input. Edit only blue cells. Source in column D.
A4: ECONOMIC
A5: CPI inflation | B5: 0.025 | D5: Pete lock table; HK 2006-25 avg 2.52%
A6: Wage growth — Adrian | B6: 0.03 | D6: Pete lock table
A7: Wage growth — Carmen | B7: 0.03 | D7: Pete lock table
A8: Education escalation (overseas) | B8: 0.05 | D8: Pete lock table
A9: RETURNS (nominal)
A10: Equities | B10: 0.06 | D10: Fahtai 27 Sep: conservative vs Pete's 7.0%
A11: Equity volatility | B11: 0.17 | D11: Pete lock table 16-18%
A12: Bonds / IG | B12: 0.04 | D12: Pete lock table
A13: Treasury ladder | B13: 0.04 | D13: held to maturity, vol ~2%
A14: MPF | B14: 0.05 | D14: Pete lock table
A15: Cash — time deposits | B15: 0.028 | D15: Pete: 3.0% 2027-28 -> 2.5% by 2031
A16: Cash — idle balances | B16: 0.002 | D16: Pete lock table
A17: TAX 2026/27
A18: Basic allowance | B18: 145000 | D18: IR (Amendment) Ordinance 2026
A19: Married allowance | B19: 290000 | D19: IR (Amendment) Ordinance 2026
A20: Child allowance | B20: 140000 | D20: IR (Amendment) Ordinance 2026
A21: Dependent parent 60+ (each) | B21: 55000 | D21: 2 parents assumed, claimed by Adrian
A22: MPF deduction cap | B22: 18000 | D22: per person
A23: Top marginal rate | B23: 0.17 | D23: progressive 2/6/10/14 then 17
A24: Tax on first 200,000 | B24: 16000 | D24: 2%+6%+10%+14% on 50k bands
A25: Mortgage rate (for HLI deduction) | B25: 0.035 | D25: Pete lock table
A26: FAMILY
A27: Adrian's salary | B27: 1050000 | D27: case
A28: Adrian's bonus (planning = low end) | B28: 150000 | D28: case 150-300k; conservative
A29: Carmen's salary / dividend | B29: 720000 | D29: case; treated as all salary
A30: Ryan's salary (EXCLUDED from base case) | B30: 300000 | D30: case; Goal 3 treats him separately
A31: Household expenses (annual) | B31: 984000 | D31: case 82,000/month
A32: Retirement spending (today money) | B32: 780000 | D32: case
A33: Retirement income floor % | B33: 0.4 | D33: Pete, C&SD HES 2024/25 top quartile
A34: MODEL LEVERS
A35: Portfolio return — plan (nominal) | B35: 0.048 | D35: mix 2: 40% eq @6% + 60% ladder @4%
A36: Portfolio return — status quo (nominal) | B36: 0.042 | D36: unmanaged, cash-heavy. TEAM TO AGREE
A37: Emergency reserve target (months) | B37: 12 | D37: vs 30.5 today
A38: Annuity purchase cost at 2037 | B38: 4120000 | D38: Pete: MPF 2.31M (A) + 1.81M (C)
A39: Annuity income (HKMC, annual) | B39: 268000 | D39: Pete: HKMC payout at 65
A40: Education — overseas annual (today) | B40: 600000 | D40: case high end, conservative
A41: Education — years | B41: 4 | D41: 4-year degree
A42: Insurance premiums (Lookbua, TBC) | B42: 113600 | D42: parents' new cover, avg a year to 2036: DI 37K, term life 7K, CI 1.5M each ~55K avg (needs-based, Bowtie Aug 2026), VHIS 15K. Paid until Adrian retires
A43: MEDICAL (methodology §1)
A44: Medical plan (1 = Flexi, 2 = Standard, 0 = off) | B44: 1 | D44: methodology §1c: Flexi median is the realistic tier
A45: Medical trend — near term (2027) | B45: 0.1 | D45: methodology §1b: WTW 9.9% / MMB 10.5%
A46: Medical trend — long run | B46: 0.06 | D46: methodology §1b: GDP per capita 4% + excess 2pp
A47: Medical trend — long run reached (year) | B47: 2036 | D47: methodology §1b: linear grade
A48: Medical trend — stress (flat) | B48: 0.0854 | D48: methodology §1b: WTW HK mean 2020-26
A49: Use medical stress in base (1/0) | B49: 0 | D49: 0 = base trend path
A50: Premiums already inside the 780,000 (today money) | B50: 65000 | D50: ~ both parents' Flexi median at 65. TEAM TO AGREE
A51: Medical plan review: switch to Standard (year) | B51: 2047 | D51: Adrian 75, Carmen 70: the tier review in the plan
A52: Guardrails: lowest discretionary share | B52: 0.5 | D52: Guyton-Klinger cuts stop at half of discretionary spending
A53: BACKSTOPS (values; switch on to include in base)
A54: Survivor spending after Adrian (share) | B54: 0.7 | D54: planning convention for a one-person household. TEAM TO AGREE
A55: Use survivor spending in base (1/0) | B55: 0 | D55: 0 = couple's spending continues to the horizon
A56: Carmen's business: net sale proceeds | B56: 3000000 | D56: Pete brief: realisable 3.0-3.5M, low end
A57: Carmen's business: sale year | B57: 2039 | D57: Carmen retires at 62
A58: Use business sale in base (1/0) | B58: 0 | D58: 0 = business held outside the plan
A59: Reverse mortgage: annual income (level) | B59: 230000 | D59: Pete brief: HKMC RMP 230-260K a year, low end
A60: Reverse mortgage: first year | B60: 2037 | D60: Adrian retires
A61: Use reverse mortgage in base (1/0) | B61: 0 | D61: 0 = home held outside the plan
A62: STRESS SCENARIOS (methodology §5)
A63: Stress: equities | B63: 0.04 | D63: Pete lock table
A64: Stress: bonds / ladder | B64: 0.025 | D64: Pete lock table (IG bonds)
A65: Stress: CPI | B65: 0.035 | D65: Pete lock table; Fed 2026 PCE 3.7%
A66: PROPERTY OPTIONS (Lookbua §9)
A67: Home value today | B67: 11500000 | D67: case
A68: Property growth | B68: 0.015 | D68: Pete lock table
A69: RMP: loan rate (fixed) | B69: 0.04 | D69: HKMC fixed plan, first 30 years
A70: RMP: insurance on balance (a year) | B70: 0.0125 | D70: HKMC
A71: RMP: upfront insurance (share of value) | B71: 0.0196 | D71: HKMC: 7 x 0.28%
A72: RMP: value counted in full up to | B72: 8000000 | D72: HKMC valuation cap
A73: RMP: share of value counted above that | B73: 0.5 | D73: HKMC valuation cap
A74: Downsize: new home price (today money) | B74: 7000000 | D74: Lookbua: smaller flat, same district. TEAM TO AGREE
A75: Downsize: stamp duty on purchase | B75: 0.0375 | D75: approx. scale for a HK$6-9M flat; verify
A76: Downsize: agents and legal (both sides) | B76: 0.02 | D76: 1% each side
A77: Downsize: moving and refit | B77: 200000 | D77: estimate
A78: Downsize: year | B78: 2037 | D78: same decision point as the reverse mortgage
A79: DATES
A80: Base year | B80: 2026 | D80: model start
A81: Adrian retires (age 65) | B81: 2037 | D81: case
A82: Carmen retires (age 62) | B82: 2039 | D82: case
A83: Chloe starts university | B83: 2028 | D83: age 18
A84: Adrian life expectancy (year, age 84) | B84: 2056 | D84: case: male 84
A85: Carmen age 89 | B85: 2066 | D85: base horizon
A86: Carmen age 95 | B86: 2072 | D86: stress horizon

Sheet BalanceSheet
A1: Balance sheet — case validation
A3: LIQUID
A4: Savings and current accounts | B4: 620000
A5: Time deposits | B5: 1480000
A6: Money market / short bond fund | B6: 400000
A7: Total liquid | B7: =SUM(B4:B6) -> 2500000
A8: INVESTMENT
A9: HK equity funds | B9: 1000000
A10: Global equity funds | B10: 1350000
A11: Investment-grade bond funds | B11: 900000
A12: ESG / sustainable equity funds | B12: 700000
A13: Green / sustainable bond products | B13: 450000
A14: Listed stocks and REITs | B14: 800000
A15: Adrian's MPF | B15: 1050000
A16: Carmen's MPF | B16: 620000
A17: Ryan's MPF | B17: 180000
A18: Digital assets (all Ryan) | B18: 500000
A19: Cash value of life policies | B19: 420000
A20: Total investment | B20: =SUM(B9:B19) -> 7970000
A21: FIXED
A22: Residential property | B22: 11500000
A23: Carmen's business | B23: 5000000
A24: Motor vehicle | B24: 220000
A25: Total fixed | B25: =SUM(B22:B24) -> 16720000
A26: LIABILITIES
A27: Mortgage | B27: 1800000
A28: Business term loan | B28: 900000
A29: Credit card / revolving | B29: 85000
A30: Total liabilities | B30: =SUM(B27:B29) -> 2785000
A32: TOTAL ASSETS | B32: =B7+B20+B25 -> 27190000
A33: NET WORTH | B33: =B32-B30 -> 24405000
A35: CHECK vs case (should be 0) | B35: =B33-24405000 -> 0
A37: Parents' investable pool (ex Ryan's MPF and digital) | B37: =B7+B20-B17-B18 -> 9790000

Sheet Tax
A1: Salaries tax 2026/27 — separate vs joint assessment
A2: Confirms Pete: separate beats joint by exactly HK$18,000
A4: HLI total (mortgage x rate) | B4: =BalanceSheet!B27*Inputs!$B$25 -> 63000
B6: Adrian | C6: Carmen | D6: Joint | E6: Ryan
A7: Income | B7: =Inputs!$B$27+Inputs!$B$28 -> 1200000 | C7: =Inputs!$B$29 -> 720000 | D7: =B7+C7 -> 1920000 | E7: =Inputs!$B$30 -> 300000
A8: less MPF | B8: =-Inputs!$B$22 -> -18000 | C8: =-Inputs!$B$22 -> -18000 | D8: =B8+C8 -> -36000 | E8: =-MIN(Inputs!$B$22,E7*0.05) -> -15000
A9: less home loan int | B9: =-$B$4/2 -> -31500 | C9: =-$B$4/2 -> -31500 | D9: =B9+C9 -> -63000 | E9: 0
A10: Net income | B10: =SUM(B7:B9) -> 1150500 | C10: =SUM(C7:C9) -> 670500 | D10: =SUM(D7:D9) -> 1821000 | E10: =SUM(E7:E9) -> 285000
A11: less allowances | B11: =-(Inputs!$B$18+Inputs!$B$20+2*Inputs!$B$21) -> -395000 | C11: =-Inputs!$B$18 -> -145000 | D11: =-(Inputs!$B$19+Inputs!$B$20+2*Inputs!$B$21) -> -540000 | E11: =-Inputs!$B$18 -> -145000
A12: Net chargeable income | B12: =MAX(B10+B11,0) -> 755500 | C12: =MAX(C10+C11,0) -> 525500 | D12: =MAX(D10+D11,0) -> 1281000 | E12: =MAX(E10+E11,0) -> 140000
A13: TAX (progressive) | B13: =IF(B12>200000,Inputs!$B$24+(B12-200000)*Inputs!$B$23,IF(B12>150000,9000+(B12-150000)*0.14,IF(B12>100000,4000+(B12-100000)*0.1,IF(B12>50000,1000+(B12-50000)*0.06,B12*0.02)))) -> 110435 | C13: =IF(C12>200000,Inputs!$B$24+(C12-200000)*Inputs!$B$23,IF(C12>150000,9000+(C12-150000)*0.14,IF(C12>100000,4000+(C12-100000)*0.1,IF(C12>50000,1000+(C12-50000)*0.06,C12*0.02)))) -> 71335 | D13: =IF(D12>200000,Inputs!$B$24+(D12-200000)*Inputs!$B$23,IF(D12>150000,9000+(D12-150000)*0.14,IF(D12>100000,4000+(D12-100000)*0.1,IF(D12>50000,1000+(D12-50000)*0.06,D12*0.02)))) -> 199770 | E13: =IF(E12>200000,Inputs!$B$24+(E12-200000)*Inputs!$B$23,IF(E12>150000,9000+(E12-150000)*0.14,IF(E12>100000,4000+(E12-100000)*0.1,IF(E12>50000,1000+(E12-50000)*0.06,E12*0.02)))) -> 8000
A15: COUPLE — separate | B15: =B13+C13 -> 181770
A16: COUPLE — joint | B16: =D13 -> 199770
A17: Separate saves | B17: =B16-B15 -> 18000
A19: CHECK separate = 181,770 | B19: =B15-181770 -> 0
A20: CHECK joint = 199,770 | B20: =B16-199770 -> 0
A22: ANNUAL SURPLUS (parents, after tax and MPF)
A23: Gross income | B23: =D7 -> 1920000
A24: less tax | B24: =-B15 -> -181770
A25: less MPF | B25: =D8 -> -36000
A26: less expenses | B26: =-Inputs!$B$31 -> -984000
A27: SURPLUS | B27: =SUM(B23:B26) -> 718230

Sheet Medical
A1: Medical premiums — VHIS age curve x medical trend (methodology §1)
A2: Blue = VHIS dataset medians (HK$ a year, dataset prices). Everything else is formula.
A4: Age | B4: Flexi median, male | C4: Flexi median, female | D4: Standard median, male | F4: Source: Health Bureau VHIS standard-premium dataset, standalone non-smoker
A5: 55 | B5: 17140 | C5: 18186 | D5: 6119
A6: 60 | B6: 23050 | C6: 23210 | D6: 7887
A7: 62 | B7: 26578 | C7: 25895 | D7: 8765
A8: 65 | B8: 32542 | C8: 31599 | D8: 10452
A9: 70 | B9: 42122 | C9: 40990 | D9: 13008
A10: 75 | B10: 53887 | C10: 53228 | D10: 16184
A11: 80 | B11: 63644 | C11: 62772 | D11: 18920
A12: Growth a year beyond 80 (75→80 slope) | B12: =(B11/B10)^(1/5)-1 -> 0.03384324 | C12: =(C11/C10)^(1/5)-1 -> 0.033534941 | D12: =(D11/D10)^(1/5)-1 -> 0.03173236
A14: Age | B14: Flexi, male | C14: Flexi, female | D14: Standard
A15: 55 | B15: =B5 -> 17140 | C15: =C5 -> 18186 | D15: =D5 -> 6119
A16: 56 | B16: =B5*(B6/B5)^((56-55)/(60-55)) -> 18186.237 | C16: =C5*(C6/C5)^((56-55)/(60-55)) -> 19095.225 | D16: =D5*(D6/D5)^((56-55)/(60-55)) -> 6437.6407
A17: 57 | B17: =B5*(B6/B5)^((57-55)/(60-55)) -> 19296.336 | C17: =C5*(C6/C5)^((57-55)/(60-55)) -> 20049.907 | D17: =D5*(D6/D5)^((57-55)/(60-55)) -> 6772.8742
A18: 58 | B18: =B5*(B6/B5)^((58-55)/(60-55)) -> 20474.197 | C18: =C5*(C6/C5)^((58-55)/(60-55)) -> 21052.32 | D18: =D5*(D6/D5)^((58-55)/(60-55)) -> 7125.5647
A19: 59 | B19: =B5*(B6/B5)^((59-55)/(60-55)) -> 21723.956 | C19: =C5*(C6/C5)^((59-55)/(60-55)) -> 22104.849 | D19: =D5*(D6/D5)^((59-55)/(60-55)) -> 7496.6211
A20: 60 | B20: =B6 -> 23050 | C20: =C6 -> 23210 | D20: =D6 -> 7887
A21: 61 | B21: =B6*(B7/B6)^((61-60)/(62-60)) -> 24751.22 | C21: =C6*(C7/C6)^((61-60)/(62-60)) -> 24515.769 | D21: =D6*(D7/D6)^((61-60)/(62-60)) -> 8314.4185
A22: 62 | B22: =B7 -> 26578 | C22: =C7 -> 25895 | D22: =D7 -> 8765
A23: 63 | B23: =B7*(B8/B7)^((63-62)/(65-62)) -> 28433.453 | C23: =C7*(C8/C7)^((63-62)/(65-62)) -> 27671.65 | D23: =D7*(D8/D7)^((63-62)/(65-62)) -> 9294.6794
A24: 64 | B24: =B7*(B8/B7)^((64-62)/(65-62)) -> 30418.439 | C24: =C7*(C8/C7)^((64-62)/(65-62)) -> 29570.196 | D24: =D7*(D8/D7)^((64-62)/(65-62)) -> 9856.3679
A25: 65 | B25: =B8 -> 32542 | C25: =C8 -> 31599 | D25: =D8 -> 10452
A26: 66 | B26: =B8*(B9/B8)^((66-65)/(70-65)) -> 34265.509 | C26: =C8*(C9/C8)^((66-65)/(70-65)) -> 33286.969 | D26: =D8*(D9/D8)^((66-65)/(70-65)) -> 10919.472
A27: 67 | B27: =B8*(B9/B8)^((67-65)/(70-65)) -> 36080.3 | C27: =C8*(C9/C8)^((67-65)/(70-65)) -> 35065.107 | D27: =D8*(D9/D8)^((67-65)/(70-65)) -> 11407.851
A28: 68 | B28: =B8*(B9/B8)^((68-65)/(70-65)) -> 37991.207 | C28: =C8*(C9/C8)^((68-65)/(70-65)) -> 36938.23 | D28: =D8*(D9/D8)^((68-65)/(70-65)) -> 11918.074
A29: 69 | B29: =B8*(B9/B8)^((69-65)/(70-65)) -> 40003.32 | C29: =C8*(C9/C8)^((69-65)/(70-65)) -> 38911.413 | D29: =D8*(D9/D8)^((69-65)/(70-65)) -> 12451.117
A30: 70 | B30: =B9 -> 42122 | C30: =C9 -> 40990 | D30: =D9 -> 13008
A31: 71 | B31: =B9*(B10/B9)^((71-70)/(75-70)) -> 44249.054 | C31: =C9*(C10/C9)^((71-70)/(75-70)) -> 43188.723 | D31: =D9*(D10/D9)^((71-70)/(75-70)) -> 13588.94
A32: 72 | B32: =B9*(B10/B9)^((72-70)/(75-70)) -> 46483.518 | C32: =C9*(C10/C9)^((72-70)/(75-70)) -> 45505.387 | D32: =D9*(D10/D9)^((72-70)/(75-70)) -> 14195.826
A33: 73 | B33: =B9*(B10/B9)^((73-70)/(75-70)) -> 48830.818 | C33: =C9*(C10/C9)^((73-70)/(75-70)) -> 47946.317 | D33: =D9*(D10/D9)^((73-70)/(75-70)) -> 14829.815
A34: 74 | B34: =B9*(B10/B9)^((74-70)/(75-70)) -> 51296.65 | C34: =C9*(C10/C9)^((74-70)/(75-70)) -> 50518.181 | D34: =D9*(D10/D9)^((74-70)/(75-70)) -> 15492.118
A35: 75 | B35: =B10 -> 53887 | C35: =C10 -> 53228 | D35: =D10 -> 16184
A36: 76 | B36: =B10*(B11/B10)^((76-75)/(80-75)) -> 55710.711 | C36: =C10*(C11/C10)^((76-75)/(80-75)) -> 55012.998 | D36: =D10*(D11/D10)^((76-75)/(80-75)) -> 16697.557
A37: 77 | B37: =B10*(B11/B10)^((77-75)/(80-75)) -> 57596.142 | C37: =C10*(C11/C10)^((77-75)/(80-75)) -> 56857.855 | D37: =D10*(D11/D10)^((77-75)/(80-75)) -> 17227.409
A38: 78 | B38: =B10*(B11/B10)^((78-75)/(80-75)) -> 59545.382 | C38: =C10*(C11/C10)^((78-75)/(80-75)) -> 58764.58 | D38: =D10*(D11/D10)^((78-75)/(80-75)) -> 17774.076
A39: 79 | B39: =B10*(B11/B10)^((79-75)/(80-75)) -> 61560.59 | C39: =C10*(C11/C10)^((79-75)/(80-75)) -> 60735.247 | D39: =D10*(D11/D10)^((79-75)/(80-75)) -> 18338.089
A40: 80 | B40: =B11 -> 63644 | C40: =C11 -> 62772 | D40: =D11 -> 18920
A41: 81 | B41: =B40*(1+B$12) -> 65797.919 | C41: =C40*(1+C$12) -> 64877.055 | D41: =D40*(1+D$12) -> 19520.376
A42: 82 | B42: =B41*(1+B$12) -> 68024.734 | C42: =C41*(1+C$12) -> 67052.704 | D42: =D41*(1+D$12) -> 20139.804
A43: 83 | B43: =B42*(1+B$12) -> 70326.911 | C43: =C42*(1+C$12) -> 69301.312 | D43: =D42*(1+D$12) -> 20778.887
A44: 84 | B44: =B43*(1+B$12) -> 72707.002 | C44: =C43*(1+C$12) -> 71625.327 | D44: =D43*(1+D$12) -> 21438.251
A45: 85 | B45: =B44*(1+B$12) -> 75167.642 | C45: =C44*(1+C$12) -> 74027.279 | D45: =D44*(1+D$12) -> 22118.537
A46: 86 | B46: =B45*(1+B$12) -> 77711.559 | C46: =C45*(1+C$12) -> 76509.779 | D46: =D45*(1+D$12) -> 22820.41
A47: 87 | B47: =B46*(1+B$12) -> 80341.57 | C47: =C46*(1+C$12) -> 79075.53 | D47: =D46*(1+D$12) -> 23544.556
A48: 88 | B48: =B47*(1+B$12) -> 83060.589 | C48: =C47*(1+C$12) -> 81727.323 | D48: =D47*(1+D$12) -> 24291.68
A49: 89 | B49: =B48*(1+B$12) -> 85871.628 | C49: =C48*(1+C$12) -> 84468.044 | D49: =D48*(1+D$12) -> 25062.512
A50: 90 | B50: =B49*(1+B$12) -> 88777.802 | C50: =C49*(1+C$12) -> 87300.675 | D50: =D49*(1+D$12) -> 25857.805
A51: 91 | B51: =B50*(1+B$12) -> 91782.331 | C51: =C50*(1+C$12) -> 90228.298 | D51: =D50*(1+D$12) -> 26678.334
A52: 92 | B52: =B51*(1+B$12) -> 94888.542 | C52: =C51*(1+C$12) -> 93254.099 | D52: =D51*(1+D$12) -> 27524.901
... A60: 100 | B60: =B59*(1+B$12) -> 123837.25 | C60: =C59*(1+C$12) -> 121414.13 | D60: =D59*(1+D$12) -> 35339.645
A62: Year | B62: Age A | C62: Age C | D62: Trend | E62: Index | F62: Adrian (dataset prices) | G62: Carmen (dataset prices) | H62: Gross premiums (nominal) | I62: Already in 780,000 (nominal) | J62: Net medical line (nominal)
A63: 2026 | B63: =$A63-1972 -> 54 | C63: =$A63-1977 -> 49 | D63: =IF($A63=Inputs!$B$80,0,IF(Inputs!$B$49=1,Inputs!$B$48,IF($A63>=Inputs!$B$47,Inputs!$B$46,Inputs!$B$45-(Inputs!$B$45-Inputs!$B$46)*($A63-(Inputs!$B$80+1))/(Inputs!$B$47-(Inputs!$B$80+1))))) -> 0 | E63: 1 | F63: =IF(OR(Inputs!$B$44=0,$A63<Inputs!$B$81,$A63>Inputs!$B$84),0,IF(Inputs!$B$44=1,INDEX($B$15:$B$60,MATCH(B63,$A$15:$A$60,0)),INDEX($D$15:$D$60,MATCH(B63,$A$15:$A$60,0)))) -> 0 | G63: =IF(OR(Inputs!$B$44=0,$A63<Inputs!$B$82),0,IF(Inputs!$B$44=1,INDEX($C$15:$C$60,MATCH(C63,$A$15:$A$60,0)),INDEX($D$15:$D$60,MATCH(C63,$A$15:$A$60,0)))) -> 0 | H63: =(F63+G63)*E63 -> 0 | I63: =IF(OR(Inputs!$B$44=0,$A63<Inputs!$B$81),0,Inputs!$B$50*(1+Inputs!$B$5)^($A63-Inputs!$B$80)) -> 0 | J63: =MAX(H63-I63,0) -> 0
A64: 2027 | B64: =$A64-1972 -> 55 | C64: =$A64-1977 -> 50 | D64: =IF($A64=Inputs!$B$80,0,IF(Inputs!$B$49=1,Inputs!$B$48,IF($A64>=Inputs!$B$47,Inputs!$B$46,Inputs!$B$45-(Inputs!$B$45-Inputs!$B$46)*($A64-(Inputs!$B$80+1))/(Inputs!$B$47-(Inputs!$B$80+1))))) -> 0.1 | E64: =E63*(1+D64) -> 1.1 | F64: =IF(OR(Inputs!$B$44=0,$A64<Inputs!$B$81,$A64>Inputs!$B$84),0,IF(Inputs!$B$44=1,INDEX($B$15:$B$60,MATCH(B64,$A$15:$A$60,0)),INDEX($D$15:$D$60,MATCH(B64,$A$15:$A$60,0)))) -> 0 | G64: =IF(OR(Inputs!$B$44=0,$A64<Inputs!$B$82),0,IF(Inputs!$B$44=1,INDEX($C$15:$C$60,MATCH(C64,$A$15:$A$60,0)),INDEX($D$15:$D$60,MATCH(C64,$A$15:$A$60,0)))) -> 0 | H64: =(F64+G64)*E64 -> 0 | I64: =IF(OR(Inputs!$B$44=0,$A64<Inputs!$B$81),0,Inputs!$B$50*(1+Inputs!$B$5)^($A64-Inputs!$B$80)) -> 0 | J64: =MAX(H64-I64,0) -> 0
A65: 2028 | B65: =$A65-1972 -> 56 | C65: =$A65-1977 -> 51 | D65: =IF($A65=Inputs!$B$80,0,IF(Inputs!$B$49=1,Inputs!$B$48,IF($A65>=Inputs!$B$47,Inputs!$B$46,Inputs!$B$45-(Inputs!$B$45-Inputs!$B$46)*($A65-(Inputs!$B$80+1))/(Inputs!$B$47-(Inputs!$B$80+1))))) -> 0.095555556 | E65: =E64*(1+D65) -> 1.2051111 | F65: =IF(OR(Inputs!$B$44=0,$A65<Inputs!$B$81,$A65>Inputs!$B$84),0,IF(Inputs!$B$44=1,INDEX($B$15:$B$60,MATCH(B65,$A$15:$A$60,0)),INDEX($D$15:$D$60,MATCH(B65,$A$15:$A$60,0)))) -> 0 | G65: =IF(OR(Inputs!$B$44=0,$A65<Inputs!$B$82),0,IF(Inputs!$B$44=1,INDEX($C$15:$C$60,MATCH(C65,$A$15:$A$60,0)),INDEX($D$15:$D$60,MATCH(C65,$A$15:$A$60,0)))) -> 0 | H65: =(F65+G65)*E65 -> 0 | I65: =IF(OR(Inputs!$B$44=0,$A65<Inputs!$B$81),0,Inputs!$B$50*(1+Inputs!$B$5)^($A65-Inputs!$B$80)) -> 0 | J65: =MAX(H65-I65,0) -> 0
A66: 2029 | B66: =$A66-1972 -> 57 | C66: =$A66-1977 -> 52 | D66: =IF($A66=Inputs!$B$80,0,IF(Inputs!$B$49=1,Inputs!$B$48,IF($A66>=Inputs!$B$47,Inputs!$B$46,Inputs!$B$45-(Inputs!$B$45-Inputs!$B$46)*($A66-(Inputs!$B$80+1))/(Inputs!$B$47-(Inputs!$B$80+1))))) -> 0.091111111 | E66: =E65*(1+D66) -> 1.3149101 | F66: =IF(OR(Inputs!$B$44=0,$A66<Inputs!$B$81,$A66>Inputs!$B$84),0,IF(Inputs!$B$44=1,INDEX($B$15:$B$60,MATCH(B66,$A$15:$A$60,0)),INDEX($D$15:$D$60,MATCH(B66,$A$15:$A$60,0)))) -> 0 | G66: =IF(OR(Inputs!$B$44=0,$A66<Inputs!$B$82),0,IF(Inputs!$B$44=1,INDEX($C$15:$C$60,MATCH(C66,$A$15:$A$60,0)),INDEX($D$15:$D$60,MATCH(C66,$A$15:$A$60,0)))) -> 0 | H66: =(F66+G66)*E66 -> 0 | I66: =IF(OR(Inputs!$B$44=0,$A66<Inputs!$B$81),0,Inputs!$B$50*(1+Inputs!$B$5)^($A66-Inputs!$B$80)) -> 0 | J66: =MAX(H66-I66,0) -> 0
A67: 2030 | B67: =$A67-1972 -> 58 | C67: =$A67-1977 -> 53 | D67: =IF($A67=Inputs!$B$80,0,IF(Inputs!$B$49=1,Inputs!$B$48,IF($A67>=Inputs!$B$47,Inputs!$B$46,Inputs!$B$45-(Inputs!$B$45-Inputs!$B$46)*($A67-(Inputs!$B$80+1))/(Inputs!$B$47-(Inputs!$B$80+1))))) -> 0.086666667 | E67: =E66*(1+D67) -> 1.428869 | F67: =IF(OR(Inputs!$B$44=0,$A67<Inputs!$B$81,$A67>Inputs!$B$84),0,IF(Inputs!$B$44=1,INDEX($B$15:$B$60,MATCH(B67,$A$15:$A$60,0)),INDEX($D$15:$D$60,MATCH(B67,$A$15:$A$60,0)))) -> 0 | G67: =IF(OR(Inputs!$B$44=0,$A67<Inputs!$B$82),0,IF(Inputs!$B$44=1,INDEX($C$15:$C$60,MATCH(C67,$A$15:$A$60,0)),INDEX($D$15:$D$60,MATCH(C67,$A$15:$A$60,0)))) -> 0 | H67: =(F67+G67)*E67 -> 0 | I67: =IF(OR(Inputs!$B$44=0,$A67<Inputs!$B$81),0,Inputs!$B$50*(1+Inputs!$B$5)^($A67-Inputs!$B$80)) -> 0 | J67: =MAX(H67-I67,0) -> 0
A68: 2031 | B68: =$A68-1972 -> 59 | C68: =$A68-1977 -> 54 | D68: =IF($A68=Inputs!$B$80,0,IF(Inputs!$B$49=1,Inputs!$B$48,IF($A68>=Inputs!$B$47,Inputs!$B$46,Inputs!$B$45-(Inputs!$B$45-Inputs!$B$46)*($A68-(Inputs!$B$80+1))/(Inputs!$B$47-(Inputs!$B$80+1))))) -> 0.082222222 | E68: =E67*(1+D68) -> 1.5463538 | F68: =IF(OR(Inputs!$B$44=0,$A68<Inputs!$B$81,$A68>Inputs!$B$84),0,IF(Inputs!$B$44=1,INDEX($B$15:$B$60,MATCH(B68,$A$15:$A$60,0)),INDEX($D$15:$D$60,MATCH(B68,$A$15:$A$60,0)))) -> 0 | G68: =IF(OR(Inputs!$B$44=0,$A68<Inputs!$B$82),0,IF(Inputs!$B$44=1,INDEX($C$15:$C$60,MATCH(C68,$A$15:$A$60,0)),INDEX($D$15:$D$60,MATCH(C68,$A$15:$A$60,0)))) -> 0 | H68: =(F68+G68)*E68 -> 0 | I68: =IF(OR(Inputs!$B$44=0,$A68<Inputs!$B$81),0,Inputs!$B$50*(1+Inputs!$B$5)^($A68-Inputs!$B$80)) -> 0 | J68: =MAX(H68-I68,0) -> 0
A69: 2032 | B69: =$A69-1972 -> 60 | C69: =$A69-1977 -> 55 | D69: =IF($A69=Inputs!$B$80,0,IF(Inputs!$B$49=1,Inputs!$B$48,IF($A69>=Inputs!$B$47,Inputs!$B$46,Inputs!$B$45-(Inputs!$B$45-Inputs!$B$46)*($A69-(Inputs!$B$80+1))/(Inputs!$B$47-(Inputs!$B$80+1))))) -> 0.077777778 | E69: =E68*(1+D69) -> 1.6666257 | F69: =IF(OR(Inputs!$B$44=0,$A69<Inputs!$B$81,$A69>Inputs!$B$84),0,IF(Inputs!$B$44=1,INDEX($B$15:$B$60,MATCH(B69,$A$15:$A$60,0)),INDEX($D$15:$D$60,MATCH(B69,$A$15:$A$60,0)))) -> 0 | G69: =IF(OR(Inputs!$B$44=0,$A69<Inputs!$B$82),0,IF(Inputs!$B$44=1,INDEX($C$15:$C$60,MATCH(C69,$A$15:$A$60,0)),INDEX($D$15:$D$60,MATCH(C69,$A$15:$A$60,0)))) -> 0 | H69: =(F69+G69)*E69 -> 0 | I69: =IF(OR(Inputs!$B$44=0,$A69<Inputs!$B$81),0,Inputs!$B$50*(1+Inputs!$B$5)^($A69-Inputs!$B$80)) -> 0 | J69: =MAX(H69-I69,0) -> 0
A70: 2033 | B70: =$A70-1972 -> 61 | C70: =$A70-1977 -> 56 | D70: =IF($A70=Inputs!$B$80,0,IF(Inputs!$B$49=1,Inputs!$B$48,IF($A70>=Inputs!$B$47,Inputs!$B$46,Inputs!$B$45-(Inputs!$B$45-Inputs!$B$46)*($A70-(Inputs!$B$80+1))/(Inputs!$B$47-(Inputs!$B$80+1))))) -> 0.073333333 | E70: =E69*(1+D70) -> 1.788845 | F70: =IF(OR(Inputs!$B$44=0,$A70<Inputs!$B$81,$A70>Inputs!$B$84),0,IF(Inputs!$B$44=1,INDEX($B$15:$B$60,MATCH(B70,$A$15:$A$60,0)),INDEX($D$15:$D$60,MATCH(B70,$A$15:$A$60,0)))) -> 0 | G70: =IF(OR(Inputs!$B$44=0,$A70<Inputs!$B$82),0,IF(Inputs!$B$44=1,INDEX($C$15:$C$60,MATCH(C70,$A$15:$A$60,0)),INDEX($D$15:$D$60,MATCH(C70,$A$15:$A$60,0)))) -> 0 | H70: =(F70+G70)*E70 -> 0 | I70: =IF(OR(Inputs!$B$44=0,$A70<Inputs!$B$81),0,Inputs!$B$50*(1+Inputs!$B$5)^($A70-Inputs!$B$80)) -> 0 | J70: =MAX(H70-I70,0) -> 0
A71: 2034 | B71: =$A71-1972 -> 62 | C71: =$A71-1977 -> 57 | D71: =IF($A71=Inputs!$B$80,0,IF(Inputs!$B$49=1,Inputs!$B$48,IF($A71>=Inputs!$B$47,Inputs!$B$46,Inputs!$B$45-(Inputs!$B$45-Inputs!$B$46)*($A71-(Inputs!$B$80+1))/(Inputs!$B$47-(Inputs!$B$80+1))))) -> 0.068888889 | E71: =E70*(1+D71) -> 1.9120765 | F71: =IF(OR(Inputs!$B$44=0,$A71<Inputs!$B$81,$A71>Inputs!$B$84),0,IF(Inputs!$B$44=1,INDEX($B$15:$B$60,MATCH(B71,$A$15:$A$60,0)),INDEX($D$15:$D$60,MATCH(B71,$A$15:$A$60,0)))) -> 0 | G71: =IF(OR(Inputs!$B$44=0,$A71<Inputs!$B$82),0,IF(Inputs!$B$44=1,INDEX($C$15:$C$60,MATCH(C71,$A$15:$A$60,0)),INDEX($D$15:$D$60,MATCH(C71,$A$15:$A$60,0)))) -> 0 | H71: =(F71+G71)*E71 -> 0 | I71: =IF(OR(Inputs!$B$44=0,$A71<Inputs!$B$81),0,Inputs!$B$50*(1+Inputs!$B$5)^($A71-Inputs!$B$80)) -> 0 | J71: =MAX(H71-I71,0) -> 0
A72: 2035 | B72: =$A72-1972 -> 63 | C72: =$A72-1977 -> 58 | D72: =IF($A72=Inputs!$B$80,0,IF(Inputs!$B$49=1,Inputs!$B$48,IF($A72>=Inputs!$B$47,Inputs!$B$46,Inputs!$B$45-(Inputs!$B$45-Inputs!$B$46)*($A72-(Inputs!$B$80+1))/(Inputs!$B$47-(Inputs!$B$80+1))))) -> 0.064444444 | E72: =E71*(1+D72) -> 2.0352992 | F72: =IF(OR(Inputs!$B$44=0,$A72<Inputs!$B$81,$A72>Inputs!$B$84),0,IF(Inputs!$B$44=1,INDEX($B$15:$B$60,MATCH(B72,$A$15:$A$60,0)),INDEX($D$15:$D$60,MATCH(B72,$A$15:$A$60,0)))) -> 0 | G72: =IF(OR(Inputs!$B$44=0,$A72<Inputs!$B$82),0,IF(Inputs!$B$44=1,INDEX($C$15:$C$60,MATCH(C72,$A$15:$A$60,0)),INDEX($D$15:$D$60,MATCH(C72,$A$15:$A$60,0)))) -> 0 | H72: =(F72+G72)*E72 -> 0 | I72: =IF(OR(Inputs!$B$44=0,$A72<Inputs!$B$81),0,Inputs!$B$50*(1+Inputs!$B$5)^($A72-Inputs!$B$80)) -> 0 | J72: =MAX(H72-I72,0) -> 0
A73: 2036 | B73: =$A73-1972 -> 64 | C73: =$A73-1977 -> 59 | D73: =IF($A73=Inputs!$B$80,0,IF(Inputs!$B$49=1,Inputs!$B$48,IF($A73>=Inputs!$B$47,Inputs!$B$46,Inputs!$B$45-(Inputs!$B$45-Inputs!$B$46)*($A73-(Inputs!$B$80+1))/(Inputs!$B$47-(Inputs!$B$80+1))))) -> 0.06 | E73: =E72*(1+D73) -> 2.1574172 | F73: =IF(OR(Inputs!$B$44=0,$A73<Inputs!$B$81,$A73>Inputs!$B$84),0,IF(Inputs!$B$44=1,INDEX($B$15:$B$60,MATCH(B73,$A$15:$A$60,0)),INDEX($D$15:$D$60,MATCH(B73,$A$15:$A$60,0)))) -> 0 | G73: =IF(OR(Inputs!$B$44=0,$A73<Inputs!$B$82),0,IF(Inputs!$B$44=1,INDEX($C$15:$C$60,MATCH(C73,$A$15:$A$60,0)),INDEX($D$15:$D$60,MATCH(C73,$A$15:$A$60,0)))) -> 0 | H73: =(F73+G73)*E73 -> 0 | I73: =IF(OR(Inputs!$B$44=0,$A73<Inputs!$B$81),0,Inputs!$B$50*(1+Inputs!$B$5)^($A73-Inputs!$B$80)) -> 0 | J73: =MAX(H73-I73,0) -> 0
A74: 2037 | B74: =$A74-1972 -> 65 | C74: =$A74-1977 -> 60 | D74: =IF($A74=Inputs!$B$80,0,IF(Inputs!$B$49=1,Inputs!$B$48,IF($A74>=Inputs!$B$47,Inputs!$B$46,Inputs!$B$45-(Inputs!$B$45-Inputs!$B$46)*($A74-(Inputs!$B$80+1))/(Inputs!$B$47-(Inputs!$B$80+1))))) -> 0.06 | E74: =E73*(1+D74) -> 2.2868622 | F74: =IF(OR(Inputs!$B$44=0,$A74<Inputs!$B$81,$A74>Inputs!$B$84),0,IF(Inputs!$B$44=1,INDEX($B$15:$B$60,MATCH(B74,$A$15:$A$60,0)),INDEX($D$15:$D$60,MATCH(B74,$A$15:$A$60,0)))) -> 32542 | G74: =IF(OR(Inputs!$B$44=0,$A74<Inputs!$B$82),0,IF(Inputs!$B$44=1,INDEX($C$15:$C$60,MATCH(C74,$A$15:$A$60,0)),INDEX($D$15:$D$60,MATCH(C74,$A$15:$A$60,0)))) -> 0 | H74: =(F74+G74)*E74 -> 74419.07 | I74: =IF(OR(Inputs!$B$44=0,$A74<Inputs!$B$81),0,Inputs!$B$50*(1+Inputs!$B$5)^($A74-Inputs!$B$80)) -> 85285.633 | J74: =MAX(H74-I74,0) -> 0
A75: 2038 | B75: =$A75-1972 -> 66 | C75: =$A75-1977 -> 61 | D75: =IF($A75=Inputs!$B$80,0,IF(Inputs!$B$49=1,Inputs!$B$48,IF($A75>=Inputs!$B$47,Inputs!$B$46,Inputs!$B$45-(Inputs!$B$45-Inputs!$B$46)*($A75-(Inputs!$B$80+1))/(Inputs!$B$47-(Inputs!$B$80+1))))) -> 0.06 | E75: =E74*(1+D75) -> 2.4240739 | F75: =IF(OR(Inputs!$B$44=0,$A75<Inputs!$B$81,$A75>Inputs!$B$84),0,IF(Inputs!$B$44=1,INDEX($B$15:$B$60,MATCH(B75,$A$15:$A$60,0)),INDEX($D$15:$D$60,MATCH(B75,$A$15:$A$60,0)))) -> 34265.509 | G75: =IF(OR(Inputs!$B$44=0,$A75<Inputs!$B$82),0,IF(Inputs!$B$44=1,INDEX($C$15:$C$60,MATCH(C75,$A$15:$A$60,0)),INDEX($D$15:$D$60,MATCH(C75,$A$15:$A$60,0)))) -> 0 | H75: =(F75+G75)*E75 -> 83062.128 | I75: =IF(OR(Inputs!$B$44=0,$A75<Inputs!$B$81),0,Inputs!$B$50*(1+Inputs!$B$5)^($A75-Inputs!$B$80)) -> 87417.774 | J75: =MAX(H75-I75,0) -> 0
... A109: 2072 | B109: =$A109-1972 -> 100 | C109: =$A109-1977 -> 95 | D109: =IF($A109=Inputs!$B$80,0,IF(Inputs!$B$49=1,Inputs!$B$48,IF($A109>=Inputs!$B$47,Inputs!$B$46,Inputs!$B$45-(Inputs!$B$45-Inputs!$B$46)*($A109-(Inputs!$B$80+1))/(Inputs!$B$47-(Inputs!$B$80+1))))) -> 0.06 | E109: =E108*(1+D109) -> 17.577021 | F109: =IF(OR(Inputs!$B$44=0,$A109<Inputs!$B$81,$A109>Inputs!$B$84),0,IF(Inputs!$B$44=1,INDEX($B$15:$B$60,MATCH(B109,$A$15:$A$60,0)),INDEX($D$15:$D$60,MATCH(B109,$A$15:$A$60,0)))) -> 0 | G109: =IF(OR(Inputs!$B$44=0,$A109<Inputs!$B$82),0,IF(Inputs!$B$44=1,INDEX($C$15:$C$60,MATCH(C109,$A$15:$A$60,0)),INDEX($D$15:$D$60,MATCH(C109,$A$15:$A$60,0)))) -> 102954.05 | H109: =(F109+G109)*E109 -> 1809625.5 | I109: =IF(OR(Inputs!$B$44=0,$A109<Inputs!$B$81),0,Inputs!$B$50*(1+Inputs!$B$5)^($A109-Inputs!$B$80)) -> 202400.31 | J109: =MAX(H109-I109,0) -> 1607225.2

Sheet Projection
A1: Year-by-year projection 2026-2072 — every cell driven by the Inputs tab
A2: Black = formula. Change nothing here; change Inputs.
A3: Year | B3: Age A | C3: Age C | D3: Income A | E3: Income C | F3: Allow A | G3: Allow C | H3: Tax A | I3: Tax C | J3: MPF | K3: Living exp | L3: Education | M3: Retire spend | N3: Medical | O3: Annuity inc | P3: Backstops | Q3: Net cash flow | R3: Portfolio open | S3: Investment return | T3: Annuity purchase | U3: Portfolio close
A4: 2026 | B4: =$A4-1972 -> 54 | C4: =$A4-1977 -> 49 | D4: =IF($A4<Inputs!$B$81,(Inputs!$B$27+Inputs!$B$28)*(1+Inputs!$B$6)^($A4-Inputs!$B$80),0) -> 1200000 | E4: =IF($A4<Inputs!$B$82,Inputs!$B$29*(1+Inputs!$B$7)^($A4-Inputs!$B$80),0) -> 720000 | F4: =(Inputs!$B$18+Inputs!$B$20+2*Inputs!$B$21)*(1+Inputs!$B$5)^($A4-Inputs!$B$80) -> 395000 | G4: =Inputs!$B$18*(1+Inputs!$B$5)^($A4-Inputs!$B$80) -> 145000 | H4: =IF(D4=0,0,IF(MAX(D4-Inputs!$B$22-Tax!$B$4/2-F4,0)>200000,Inputs!$B$24+(MAX(D4-Inputs!$B$22-Tax!$B$4/2-F4,0)-200000)*Inputs!$B$23,IF(MAX(D4-Inputs!$B$22-Tax!$B$4/2-F4,0)>150000,9000+(MAX(D4-Inputs!$B$22-Tax!$B$4/2-F4,0)-150000)*0.14,IF(MAX(D4-Inputs!$B$22-Tax!$B$4/2-F4,0)>100000,4000+(MAX(D4-Inputs!$B$22-Tax!$B$4/2-F4,0)-100000)*0.1,IF(MAX(D4-Inputs!$B$22-Tax!$B$4/2-F4,0)>50000,1000+(MAX(D4-Inputs!$B$22-Tax!$B$4/2-F4,0)-50000)*0.06,MAX(MAX(D4-Inputs!$B$22-Tax!$B$4/2-F4,0),0)*0.02))))) -> 110435 | I4: =IF(E4=0,0,IF(MAX(E4-Inputs!$B$22-Tax!$B$4/2-G4,0)>200000,Inputs!$B$24+(MAX(E4-Inputs!$B$22-Tax!$B$4/2-G4,0)-200000)*Inputs!$B$23,IF(MAX(E4-Inputs!$B$22-Tax!$B$4/2-G4,0)>150000,9000+(MAX(E4-Inputs!$B$22-Tax!$B$4/2-G4,0)-150000)*0.14,IF(MAX(E4-Inputs!$B$22-Tax!$B$4/2-G4,0)>100000,4000+(MAX(E4-Inputs!$B$22-Tax!$B$4/2-G4,0)-100000)*0.1,IF(MAX(E4-Inputs!$B$22-Tax!$B$4/2-G4,0)>50000,1000+(MAX(E4-Inputs!$B$22-Tax!$B$4/2-G4,0)-50000)*0.06,MAX(MAX(E4-Inputs!$B$22-Tax!$B$4/2-G4,0),0)*0.02))))) -> 71335 | J4: =IF(D4>0,Inputs!$B$22,0)+IF(E4>0,Inputs!$B$22,0) -> 36000 | K4: =IF($A4<Inputs!$B$81,Inputs!$B$31*(1+Inputs!$B$5)^($A4-Inputs!$B$80),0) -> 984000 | L4: =IF(AND($A4>=Inputs!$B$83,$A4<Inputs!$B$83+Inputs!$B$41),Inputs!$B$40*(1+Inputs!$B$8)^($A4-Inputs!$B$80),0) -> 0 | M4: =IF($A4>=Inputs!$B$81,Inputs!$B$32*(1+Inputs!$B$5)^($A4-Inputs!$B$80)*IF(AND(Inputs!$B$55=1,$A4>Inputs!$B$84),Inputs!$B$54,1),0) -> 0 | N4: =INDEX(Medical!$J$63:$J$109,MATCH($A4,Medical!$A$63:$A$109,0)) -> 0 | O4: =IF($A4>=Inputs!$B$81,Inputs!$B$39,0) -> 0 | P4: =IF(AND(Inputs!$B$58=1,$A4=Inputs!$B$57),Inputs!$B$56,0)+IF(AND(Inputs!$B$61=1,$A4>=Inputs!$B$60),Inputs!$B$59,0) -> 0 | Q4: =D4+E4-H4-I4+J4-K4-L4-M4-N4+O4+P4-IF($A4<Inputs!$B$81,Inputs!$B$42,0) -> 676630 | R4: =BalanceSheet!$B$37 -> 9790000 | S4: =R4*Inputs!$B$35 -> 469920 | T4: =IF($A4=Inputs!$B$81,-Inputs!$B$38,0) -> 0 | U4: =MAX(R4+S4+Q4+T4,0) -> 10936550
A5: 2027 | B5: =$A5-1972 -> 55 | C5: =$A5-1977 -> 50 | D5: =IF($A5<Inputs!$B$81,(Inputs!$B$27+Inputs!$B$28)*(1+Inputs!$B$6)^($A5-Inputs!$B$80),0) -> 1236000 | E5: =IF($A5<Inputs!$B$82,Inputs!$B$29*(1+Inputs!$B$7)^($A5-Inputs!$B$80),0) -> 741600 | F5: =(Inputs!$B$18+Inputs!$B$20+2*Inputs!$B$21)*(1+Inputs!$B$5)^($A5-Inputs!$B$80) -> 404875 | G5: =Inputs!$B$18*(1+Inputs!$B$5)^($A5-Inputs!$B$80) -> 148625 | H5: =IF(D5=0,0,IF(MAX(D5-Inputs!$B$22-Tax!$B$4/2-F5,0)>200000,Inputs!$B$24+(MAX(D5-Inputs!$B$22-Tax!$B$4/2-F5,0)-200000)*Inputs!$B$23,IF(MAX(D5-Inputs!$B$22-Tax!$B$4/2-F5,0)>150000,9000+(MAX(D5-Inputs!$B$22-Tax!$B$4/2-F5,0)-150000)*0.14,IF(MAX(D5-Inputs!$B$22-Tax!$B$4/2-F5,0)>100000,4000+(MAX(D5-Inputs!$B$22-Tax!$B$4/2-F5,0)-100000)*0.1,IF(MAX(D5-Inputs!$B$22-Tax!$B$4/2-F5,0)>50000,1000+(MAX(D5-Inputs!$B$22-Tax!$B$4/2-F5,0)-50000)*0.06,MAX(MAX(D5-Inputs!$B$22-Tax!$B$4/2-F5,0),0)*0.02))))) -> 114876.25 | I5: =IF(E5=0,0,IF(MAX(E5-Inputs!$B$22-Tax!$B$4/2-G5,0)>200000,Inputs!$B$24+(MAX(E5-Inputs!$B$22-Tax!$B$4/2-G5,0)-200000)*Inputs!$B$23,IF(MAX(E5-Inputs!$B$22-Tax!$B$4/2-G5,0)>150000,9000+(MAX(E5-Inputs!$B$22-Tax!$B$4/2-G5,0)-150000)*0.14,IF(MAX(E5-Inputs!$B$22-Tax!$B$4/2-G5,0)>100000,4000+(MAX(E5-Inputs!$B$22-Tax!$B$4/2-G5,0)-100000)*0.1,IF(MAX(E5-Inputs!$B$22-Tax!$B$4/2-G5,0)>50000,1000+(MAX(E5-Inputs!$B$22-Tax!$B$4/2-G5,0)-50000)*0.06,MAX(MAX(E5-Inputs!$B$22-Tax!$B$4/2-G5,0),0)*0.02))))) -> 74390.75 | J5: =IF(D5>0,Inputs!$B$22,0)+IF(E5>0,Inputs!$B$22,0) -> 36000 | K5: =IF($A5<Inputs!$B$81,Inputs!$B$31*(1+Inputs!$B$5)^($A5-Inputs!$B$80),0) -> 1008600 | L5: =IF(AND($A5>=Inputs!$B$83,$A5<Inputs!$B$83+Inputs!$B$41),Inputs!$B$40*(1+Inputs!$B$8)^($A5-Inputs!$B$80),0) -> 0 | M5: =IF($A5>=Inputs!$B$81,Inputs!$B$32*(1+Inputs!$B$5)^($A5-Inputs!$B$80)*IF(AND(Inputs!$B$55=1,$A5>Inputs!$B$84),Inputs!$B$54,1),0) -> 0 | N5: =INDEX(Medical!$J$63:$J$109,MATCH($A5,Medical!$A$63:$A$109,0)) -> 0 | O5: =IF($A5>=Inputs!$B$81,Inputs!$B$39,0) -> 0 | P5: =IF(AND(Inputs!$B$58=1,$A5=Inputs!$B$57),Inputs!$B$56,0)+IF(AND(Inputs!$B$61=1,$A5>=Inputs!$B$60),Inputs!$B$59,0) -> 0 | Q5: =D5+E5-H5-I5+J5-K5-L5-M5-N5+O5+P5-IF($A5<Inputs!$B$81,Inputs!$B$42,0) -> 702133 | R5: =U4 -> 10936550 | S5: =R5*Inputs!$B$35 -> 524954.4 | T5: =IF($A5=Inputs!$B$81,-Inputs!$B$38,0) -> 0 | U5: =MAX(R5+S5+Q5+T5,0) -> 12163637
A6: 2028 | B6: =$A6-1972 -> 56 | C6: =$A6-1977 -> 51 | D6: =IF($A6<Inputs!$B$81,(Inputs!$B$27+Inputs!$B$28)*(1+Inputs!$B$6)^($A6-Inputs!$B$80),0) -> 1273080 | E6: =IF($A6<Inputs!$B$82,Inputs!$B$29*(1+Inputs!$B$7)^($A6-Inputs!$B$80),0) -> 763848 | F6: =(Inputs!$B$18+Inputs!$B$20+2*Inputs!$B$21)*(1+Inputs!$B$5)^($A6-Inputs!$B$80) -> 414996.87 | G6: =Inputs!$B$18*(1+Inputs!$B$5)^($A6-Inputs!$B$80) -> 152340.62 | H6: =IF(D6=0,0,IF(MAX(D6-Inputs!$B$22-Tax!$B$4/2-F6,0)>200000,Inputs!$B$24+(MAX(D6-Inputs!$B$22-Tax!$B$4/2-F6,0)-200000)*Inputs!$B$23,IF(MAX(D6-Inputs!$B$22-Tax!$B$4/2-F6,0)>150000,9000+(MAX(D6-Inputs!$B$22-Tax!$B$4/2-F6,0)-150000)*0.14,IF(MAX(D6-Inputs!$B$22-Tax!$B$4/2-F6,0)>100000,4000+(MAX(D6-Inputs!$B$22-Tax!$B$4/2-F6,0)-100000)*0.1,IF(MAX(D6-Inputs!$B$22-Tax!$B$4/2-F6,0)>50000,1000+(MAX(D6-Inputs!$B$22-Tax!$B$4/2-F6,0)-50000)*0.06,MAX(MAX(D6-Inputs!$B$22-Tax!$B$4/2-F6,0),0)*0.02))))) -> 119459.13 | I6: =IF(E6=0,0,IF(MAX(E6-Inputs!$B$22-Tax!$B$4/2-G6,0)>200000,Inputs!$B$24+(MAX(E6-Inputs!$B$22-Tax!$B$4/2-G6,0)-200000)*Inputs!$B$23,IF(MAX(E6-Inputs!$B$22-Tax!$B$4/2-G6,0)>150000,9000+(MAX(E6-Inputs!$B$22-Tax!$B$4/2-G6,0)-150000)*0.14,IF(MAX(E6-Inputs!$B$22-Tax!$B$4/2-G6,0)>100000,4000+(MAX(E6-Inputs!$B$22-Tax!$B$4/2-G6,0)-100000)*0.1,IF(MAX(E6-Inputs!$B$22-Tax!$B$4/2-G6,0)>50000,1000+(MAX(E6-Inputs!$B$22-Tax!$B$4/2-G6,0)-50000)*0.06,MAX(MAX(E6-Inputs!$B$22-Tax!$B$4/2-G6,0),0)*0.02))))) -> 77541.254 | J6: =IF(D6>0,Inputs!$B$22,0)+IF(E6>0,Inputs!$B$22,0) -> 36000 | K6: =IF($A6<Inputs!$B$81,Inputs!$B$31*(1+Inputs!$B$5)^($A6-Inputs!$B$80),0) -> 1033815 | L6: =IF(AND($A6>=Inputs!$B$83,$A6<Inputs!$B$83+Inputs!$B$41),Inputs!$B$40*(1+Inputs!$B$8)^($A6-Inputs!$B$80),0) -> 661500 | M6: =IF($A6>=Inputs!$B$81,Inputs!$B$32*(1+Inputs!$B$5)^($A6-Inputs!$B$80)*IF(AND(Inputs!$B$55=1,$A6>Inputs!$B$84),Inputs!$B$54,1),0) -> 0 | N6: =INDEX(Medical!$J$63:$J$109,MATCH($A6,Medical!$A$63:$A$109,0)) -> 0 | O6: =IF($A6>=Inputs!$B$81,Inputs!$B$39,0) -> 0 | P6: =IF(AND(Inputs!$B$58=1,$A6=Inputs!$B$57),Inputs!$B$56,0)+IF(AND(Inputs!$B$61=1,$A6>=Inputs!$B$60),Inputs!$B$59,0) -> 0 | Q6: =D6+E6-H6-I6+J6-K6-L6-M6-N6+O6+P6-IF($A6<Inputs!$B$81,Inputs!$B$42,0) -> 67012.615 | R6: =U5 -> 12163637 | S6: =R6*Inputs!$B$35 -> 583854.6 | T6: =IF($A6=Inputs!$B$81,-Inputs!$B$38,0) -> 0 | U6: =MAX(R6+S6+Q6+T6,0) -> 12814505
A7: 2029 | B7: =$A7-1972 -> 57 | C7: =$A7-1977 -> 52 | D7: =IF($A7<Inputs!$B$81,(Inputs!$B$27+Inputs!$B$28)*(1+Inputs!$B$6)^($A7-Inputs!$B$80),0) -> 1311272.4 | E7: =IF($A7<Inputs!$B$82,Inputs!$B$29*(1+Inputs!$B$7)^($A7-Inputs!$B$80),0) -> 786763.44 | F7: =(Inputs!$B$18+Inputs!$B$20+2*Inputs!$B$21)*(1+Inputs!$B$5)^($A7-Inputs!$B$80) -> 425371.8 | G7: =Inputs!$B$18*(1+Inputs!$B$5)^($A7-Inputs!$B$80) -> 156149.14 | H7: =IF(D7=0,0,IF(MAX(D7-Inputs!$B$22-Tax!$B$4/2-F7,0)>200000,Inputs!$B$24+(MAX(D7-Inputs!$B$22-Tax!$B$4/2-F7,0)-200000)*Inputs!$B$23,IF(MAX(D7-Inputs!$B$22-Tax!$B$4/2-F7,0)>150000,9000+(MAX(D7-Inputs!$B$22-Tax!$B$4/2-F7,0)-150000)*0.14,IF(MAX(D7-Inputs!$B$22-Tax!$B$4/2-F7,0)>100000,4000+(MAX(D7-Inputs!$B$22-Tax!$B$4/2-F7,0)-100000)*0.1,IF(MAX(D7-Inputs!$B$22-Tax!$B$4/2-F7,0)>50000,1000+(MAX(D7-Inputs!$B$22-Tax!$B$4/2-F7,0)-50000)*0.06,MAX(MAX(D7-Inputs!$B$22-Tax!$B$4/2-F7,0),0)*0.02))))) -> 124188.1 | I7: =IF(E7=0,0,IF(MAX(E7-Inputs!$B$22-Tax!$B$4/2-G7,0)>200000,Inputs!$B$24+(MAX(E7-Inputs!$B$22-Tax!$B$4/2-G7,0)-200000)*Inputs!$B$23,IF(MAX(E7-Inputs!$B$22-Tax!$B$4/2-G7,0)>150000,9000+(MAX(E7-Inputs!$B$22-Tax!$B$4/2-G7,0)-150000)*0.14,IF(MAX(E7-Inputs!$B$22-Tax!$B$4/2-G7,0)>100000,4000+(MAX(E7-Inputs!$B$22-Tax!$B$4/2-G7,0)-100000)*0.1,IF(MAX(E7-Inputs!$B$22-Tax!$B$4/2-G7,0)>50000,1000+(MAX(E7-Inputs!$B$22-Tax!$B$4/2-G7,0)-50000)*0.06,MAX(MAX(E7-Inputs!$B$22-Tax!$B$4/2-G7,0),0)*0.02))))) -> 80789.431 | J7: =IF(D7>0,Inputs!$B$22,0)+IF(E7>0,Inputs!$B$22,0) -> 36000 | K7: =IF($A7<Inputs!$B$81,Inputs!$B$31*(1+Inputs!$B$5)^($A7-Inputs!$B$80),0) -> 1059660.4 | L7: =IF(AND($A7>=Inputs!$B$83,$A7<Inputs!$B$83+Inputs!$B$41),Inputs!$B$40*(1+Inputs!$B$8)^($A7-Inputs!$B$80),0) -> 694575 | M7: =IF($A7>=Inputs!$B$81,Inputs!$B$32*(1+Inputs!$B$5)^($A7-Inputs!$B$80)*IF(AND(Inputs!$B$55=1,$A7>Inputs!$B$84),Inputs!$B$54,1),0) -> 0 | N7: =INDEX(Medical!$J$63:$J$109,MATCH($A7,Medical!$A$63:$A$109,0)) -> 0 | O7: =IF($A7>=Inputs!$B$81,Inputs!$B$39,0) -> 0 | P7: =IF(AND(Inputs!$B$58=1,$A7=Inputs!$B$57),Inputs!$B$56,0)+IF(AND(Inputs!$B$61=1,$A7>=Inputs!$B$60),Inputs!$B$59,0) -> 0 | Q7: =D7+E7-H7-I7+J7-K7-L7-M7-N7+O7+P7-IF($A7<Inputs!$B$81,Inputs!$B$42,0) -> 61222.932 | R7: =U6 -> 12814505 | S7: =R7*Inputs!$B$35 -> 615096.22 | T7: =IF($A7=Inputs!$B$81,-Inputs!$B$38,0) -> 0 | U7: =MAX(R7+S7+Q7+T7,0) -> 13490824
A8: 2030 | B8: =$A8-1972 -> 58 | C8: =$A8-1977 -> 53 | D8: =IF($A8<Inputs!$B$81,(Inputs!$B$27+Inputs!$B$28)*(1+Inputs!$B$6)^($A8-Inputs!$B$80),0) -> 1350610.6 | E8: =IF($A8<Inputs!$B$82,Inputs!$B$29*(1+Inputs!$B$7)^($A8-Inputs!$B$80),0) -> 810366.34 | F8: =(Inputs!$B$18+Inputs!$B$20+2*Inputs!$B$21)*(1+Inputs!$B$5)^($A8-Inputs!$B$80) -> 436006.09 | G8: =Inputs!$B$18*(1+Inputs!$B$5)^($A8-Inputs!$B$80) -> 160052.87 | H8: =IF(D8=0,0,IF(MAX(D8-Inputs!$B$22-Tax!$B$4/2-F8,0)>200000,Inputs!$B$24+(MAX(D8-Inputs!$B$22-Tax!$B$4/2-F8,0)-200000)*Inputs!$B$23,IF(MAX(D8-Inputs!$B$22-Tax!$B$4/2-F8,0)>150000,9000+(MAX(D8-Inputs!$B$22-Tax!$B$4/2-F8,0)-150000)*0.14,IF(MAX(D8-Inputs!$B$22-Tax!$B$4/2-F8,0)>100000,4000+(MAX(D8-Inputs!$B$22-Tax!$B$4/2-F8,0)-100000)*0.1,IF(MAX(D8-Inputs!$B$22-Tax!$B$4/2-F8,0)>50000,1000+(MAX(D8-Inputs!$B$22-Tax!$B$4/2-F8,0)-50000)*0.06,MAX(MAX(D8-Inputs!$B$22-Tax!$B$4/2-F8,0),0)*0.02))))) -> 129067.76 | I8: =IF(E8=0,0,IF(MAX(E8-Inputs!$B$22-Tax!$B$4/2-G8,0)>200000,Inputs!$B$24+(MAX(E8-Inputs!$B$22-Tax!$B$4/2-G8,0)-200000)*Inputs!$B$23,IF(MAX(E8-Inputs!$B$22-Tax!$B$4/2-G8,0)>150000,9000+(MAX(E8-Inputs!$B$22-Tax!$B$4/2-G8,0)-150000)*0.14,IF(MAX(E8-Inputs!$B$22-Tax!$B$4/2-G8,0)>100000,4000+(MAX(E8-Inputs!$B$22-Tax!$B$4/2-G8,0)-100000)*0.1,IF(MAX(E8-Inputs!$B$22-Tax!$B$4/2-G8,0)>50000,1000+(MAX(E8-Inputs!$B$22-Tax!$B$4/2-G8,0)-50000)*0.06,MAX(MAX(E8-Inputs!$B$22-Tax!$B$4/2-G8,0),0)*0.02))))) -> 84138.291 | J8: =IF(D8>0,Inputs!$B$22,0)+IF(E8>0,Inputs!$B$22,0) -> 36000 | K8: =IF($A8<Inputs!$B$81,Inputs!$B$31*(1+Inputs!$B$5)^($A8-Inputs!$B$80),0) -> 1086151.9 | L8: =IF(AND($A8>=Inputs!$B$83,$A8<Inputs!$B$83+Inputs!$B$41),Inputs!$B$40*(1+Inputs!$B$8)^($A8-Inputs!$B$80),0) -> 729303.75 | M8: =IF($A8>=Inputs!$B$81,Inputs!$B$32*(1+Inputs!$B$5)^($A8-Inputs!$B$80)*IF(AND(Inputs!$B$55=1,$A8>Inputs!$B$84),Inputs!$B$54,1),0) -> 0 | N8: =INDEX(Medical!$J$63:$J$109,MATCH($A8,Medical!$A$63:$A$109,0)) -> 0 | O8: =IF($A8>=Inputs!$B$81,Inputs!$B$39,0) -> 0 | P8: =IF(AND(Inputs!$B$58=1,$A8=Inputs!$B$57),Inputs!$B$56,0)+IF(AND(Inputs!$B$61=1,$A8>=Inputs!$B$60),Inputs!$B$59,0) -> 0 | Q8: =D8+E8-H8-I8+J8-K8-L8-M8-N8+O8+P8-IF($A8<Inputs!$B$81,Inputs!$B$42,0) -> 54715.229 | R8: =U7 -> 13490824 | S8: =R8*Inputs!$B$35 -> 647559.54 | T8: =IF($A8=Inputs!$B$81,-Inputs!$B$38,0) -> 0 | U8: =MAX(R8+S8+Q8+T8,0) -> 14193099
A9: 2031 | B9: =$A9-1972 -> 59 | C9: =$A9-1977 -> 54 | D9: =IF($A9<Inputs!$B$81,(Inputs!$B$27+Inputs!$B$28)*(1+Inputs!$B$6)^($A9-Inputs!$B$80),0) -> 1391128.9 | E9: =IF($A9<Inputs!$B$82,Inputs!$B$29*(1+Inputs!$B$7)^($A9-Inputs!$B$80),0) -> 834677.33 | F9: =(Inputs!$B$18+Inputs!$B$20+2*Inputs!$B$21)*(1+Inputs!$B$5)^($A9-Inputs!$B$80) -> 446906.24 | G9: =Inputs!$B$18*(1+Inputs!$B$5)^($A9-Inputs!$B$80) -> 164054.19 | H9: =IF(D9=0,0,IF(MAX(D9-Inputs!$B$22-Tax!$B$4/2-F9,0)>200000,Inputs!$B$24+(MAX(D9-Inputs!$B$22-Tax!$B$4/2-F9,0)-200000)*Inputs!$B$23,IF(MAX(D9-Inputs!$B$22-Tax!$B$4/2-F9,0)>150000,9000+(MAX(D9-Inputs!$B$22-Tax!$B$4/2-F9,0)-150000)*0.14,IF(MAX(D9-Inputs!$B$22-Tax!$B$4/2-F9,0)>100000,4000+(MAX(D9-Inputs!$B$22-Tax!$B$4/2-F9,0)-100000)*0.1,IF(MAX(D9-Inputs!$B$22-Tax!$B$4/2-F9,0)>50000,1000+(MAX(D9-Inputs!$B$22-Tax!$B$4/2-F9,0)-50000)*0.06,MAX(MAX(D9-Inputs!$B$22-Tax!$B$4/2-F9,0),0)*0.02))))) -> 134102.85 | I9: =IF(E9=0,0,IF(MAX(E9-Inputs!$B$22-Tax!$B$4/2-G9,0)>200000,Inputs!$B$24+(MAX(E9-Inputs!$B$22-Tax!$B$4/2-G9,0)-200000)*Inputs!$B$23,IF(MAX(E9-Inputs!$B$22-Tax!$B$4/2-G9,0)>150000,9000+(MAX(E9-Inputs!$B$22-Tax!$B$4/2-G9,0)-150000)*0.14,IF(MAX(E9-Inputs!$B$22-Tax!$B$4/2-G9,0)>100000,4000+(MAX(E9-Inputs!$B$22-Tax!$B$4/2-G9,0)-100000)*0.1,IF(MAX(E9-Inputs!$B$22-Tax!$B$4/2-G9,0)>50000,1000+(MAX(E9-Inputs!$B$22-Tax!$B$4/2-G9,0)-50000)*0.06,MAX(MAX(E9-Inputs!$B$22-Tax!$B$4/2-G9,0),0)*0.02))))) -> 87590.934 | J9: =IF(D9>0,Inputs!$B$22,0)+IF(E9>0,Inputs!$B$22,0) -> 36000 | K9: =IF($A9<Inputs!$B$81,Inputs!$B$31*(1+Inputs!$B$5)^($A9-Inputs!$B$80),0) -> 1113305.7 | L9: =IF(AND($A9>=Inputs!$B$83,$A9<Inputs!$B$83+Inputs!$B$41),Inputs!$B$40*(1+Inputs!$B$8)^($A9-Inputs!$B$80),0) -> 765768.94 | M9: =IF($A9>=Inputs!$B$81,Inputs!$B$32*(1+Inputs!$B$5)^($A9-Inputs!$B$80)*IF(AND(Inputs!$B$55=1,$A9>Inputs!$B$84),Inputs!$B$54,1),0) -> 0 | N9: =INDEX(Medical!$J$63:$J$109,MATCH($A9,Medical!$A$63:$A$109,0)) -> 0 | O9: =IF($A9>=Inputs!$B$81,Inputs!$B$39,0) -> 0 | P9: =IF(AND(Inputs!$B$58=1,$A9=Inputs!$B$57),Inputs!$B$56,0)+IF(AND(Inputs!$B$61=1,$A9>=Inputs!$B$60),Inputs!$B$59,0) -> 0 | Q9: =D9+E9-H9-I9+J9-K9-L9-M9-N9+O9+P9-IF($A9<Inputs!$B$81,Inputs!$B$42,0) -> 47437.82 | R9: =U8 -> 14193099 | S9: =R9*Inputs!$B$35 -> 681268.73 | T9: =IF($A9=Inputs!$B$81,-Inputs!$B$38,0) -> 0 | U9: =MAX(R9+S9+Q9+T9,0) -> 14921805
A10: 2032 | B10: =$A10-1972 -> 60 | C10: =$A10-1977 -> 55 | D10: =IF($A10<Inputs!$B$81,(Inputs!$B$27+Inputs!$B$28)*(1+Inputs!$B$6)^($A10-Inputs!$B$80),0) -> 1432862.8 | E10: =IF($A10<Inputs!$B$82,Inputs!$B$29*(1+Inputs!$B$7)^($A10-Inputs!$B$80),0) -> 859717.65 | F10: =(Inputs!$B$18+Inputs!$B$20+2*Inputs!$B$21)*(1+Inputs!$B$5)^($A10-Inputs!$B$80) -> 458078.9 | G10: =Inputs!$B$18*(1+Inputs!$B$5)^($A10-Inputs!$B$80) -> 168155.55 | H10: =IF(D10=0,0,IF(MAX(D10-Inputs!$B$22-Tax!$B$4/2-F10,0)>200000,Inputs!$B$24+(MAX(D10-Inputs!$B$22-Tax!$B$4/2-F10,0)-200000)*Inputs!$B$23,IF(MAX(D10-Inputs!$B$22-Tax!$B$4/2-F10,0)>150000,9000+(MAX(D10-Inputs!$B$22-Tax!$B$4/2-F10,0)-150000)*0.14,IF(MAX(D10-Inputs!$B$22-Tax!$B$4/2-F10,0)>100000,4000+(MAX(D10-Inputs!$B$22-Tax!$B$4/2-F10,0)-100000)*0.1,IF(MAX(D10-Inputs!$B$22-Tax!$B$4/2-F10,0)>50000,1000+(MAX(D10-Inputs!$B$22-Tax!$B$4/2-F10,0)-50000)*0.06,MAX(MAX(D10-Inputs!$B$22-Tax!$B$4/2-F10,0),0)*0.02))))) -> 139298.26 | I10: =IF(E10=0,0,IF(MAX(E10-Inputs!$B$22-Tax!$B$4/2-G10,0)>200000,Inputs!$B$24+(MAX(E10-Inputs!$B$22-Tax!$B$4/2-G10,0)-200000)*Inputs!$B$23,IF(MAX(E10-Inputs!$B$22-Tax!$B$4/2-G10,0)>150000,9000+(MAX(E10-Inputs!$B$22-Tax!$B$4/2-G10,0)-150000)*0.14,IF(MAX(E10-Inputs!$B$22-Tax!$B$4/2-G10,0)>100000,4000+(MAX(E10-Inputs!$B$22-Tax!$B$4/2-G10,0)-100000)*0.1,IF(MAX(E10-Inputs!$B$22-Tax!$B$4/2-G10,0)>50000,1000+(MAX(E10-Inputs!$B$22-Tax!$B$4/2-G10,0)-50000)*0.06,MAX(MAX(E10-Inputs!$B$22-Tax!$B$4/2-G10,0),0)*0.02))))) -> 91150.558 | J10: =IF(D10>0,Inputs!$B$22,0)+IF(E10>0,Inputs!$B$22,0) -> 36000 | K10: =IF($A10<Inputs!$B$81,Inputs!$B$31*(1+Inputs!$B$5)^($A10-Inputs!$B$80),0) -> 1141138.3 | L10: =IF(AND($A10>=Inputs!$B$83,$A10<Inputs!$B$83+Inputs!$B$41),Inputs!$B$40*(1+Inputs!$B$8)^($A10-Inputs!$B$80),0) -> 0 | M10: =IF($A10>=Inputs!$B$81,Inputs!$B$32*(1+Inputs!$B$5)^($A10-Inputs!$B$80)*IF(AND(Inputs!$B$55=1,$A10>Inputs!$B$84),Inputs!$B$54,1),0) -> 0 | N10: =INDEX(Medical!$J$63:$J$109,MATCH($A10,Medical!$A$63:$A$109,0)) -> 0 | O10: =IF($A10>=Inputs!$B$81,Inputs!$B$39,0) -> 0 | P10: =IF(AND(Inputs!$B$58=1,$A10=Inputs!$B$57),Inputs!$B$56,0)+IF(AND(Inputs!$B$61=1,$A10>=Inputs!$B$60),Inputs!$B$59,0) -> 0 | Q10: =D10+E10-H10-I10+J10-K10-L10-M10-N10+O10+P10-IF($A10<Inputs!$B$81,Inputs!$B$42,0) -> 843393.27 | R10: =U9 -> 14921805 | S10: =R10*Inputs!$B$35 -> 716246.64 | T10: =IF($A10=Inputs!$B$81,-Inputs!$B$38,0) -> 0 | U10: =MAX(R10+S10+Q10+T10,0) -> 16481445
A11: 2033 | B11: =$A11-1972 -> 61 | C11: =$A11-1977 -> 56 | D11: =IF($A11<Inputs!$B$81,(Inputs!$B$27+Inputs!$B$28)*(1+Inputs!$B$6)^($A11-Inputs!$B$80),0) -> 1475848.6 | E11: =IF($A11<Inputs!$B$82,Inputs!$B$29*(1+Inputs!$B$7)^($A11-Inputs!$B$80),0) -> 885509.18 | F11: =(Inputs!$B$18+Inputs!$B$20+2*Inputs!$B$21)*(1+Inputs!$B$5)^($A11-Inputs!$B$80) -> 469530.87 | G11: =Inputs!$B$18*(1+Inputs!$B$5)^($A11-Inputs!$B$80) -> 172359.43 | H11: =IF(D11=0,0,IF(MAX(D11-Inputs!$B$22-Tax!$B$4/2-F11,0)>200000,Inputs!$B$24+(MAX(D11-Inputs!$B$22-Tax!$B$4/2-F11,0)-200000)*Inputs!$B$23,IF(MAX(D11-Inputs!$B$22-Tax!$B$4/2-F11,0)>150000,9000+(MAX(D11-Inputs!$B$22-Tax!$B$4/2-F11,0)-150000)*0.14,IF(MAX(D11-Inputs!$B$22-Tax!$B$4/2-F11,0)>100000,4000+(MAX(D11-Inputs!$B$22-Tax!$B$4/2-F11,0)-100000)*0.1,IF(MAX(D11-Inputs!$B$22-Tax!$B$4/2-F11,0)>50000,1000+(MAX(D11-Inputs!$B$22-Tax!$B$4/2-F11,0)-50000)*0.06,MAX(MAX(D11-Inputs!$B$22-Tax!$B$4/2-F11,0),0)*0.02))))) -> 144659.02 | I11: =IF(E11=0,0,IF(MAX(E11-Inputs!$B$22-Tax!$B$4/2-G11,0)>200000,Inputs!$B$24+(MAX(E11-Inputs!$B$22-Tax!$B$4/2-G11,0)-200000)*Inputs!$B$23,IF(MAX(E11-Inputs!$B$22-Tax!$B$4/2-G11,0)>150000,9000+(MAX(E11-Inputs!$B$22-Tax!$B$4/2-G11,0)-150000)*0.14,IF(MAX(E11-Inputs!$B$22-Tax!$B$4/2-G11,0)>100000,4000+(MAX(E11-Inputs!$B$22-Tax!$B$4/2-G11,0)-100000)*0.1,IF(MAX(E11-Inputs!$B$22-Tax!$B$4/2-G11,0)>50000,1000+(MAX(E11-Inputs!$B$22-Tax!$B$4/2-G11,0)-50000)*0.06,MAX(MAX(E11-Inputs!$B$22-Tax!$B$4/2-G11,0),0)*0.02))))) -> 94820.457 | J11: =IF(D11>0,Inputs!$B$22,0)+IF(E11>0,Inputs!$B$22,0) -> 36000 | K11: =IF($A11<Inputs!$B$81,Inputs!$B$31*(1+Inputs!$B$5)^($A11-Inputs!$B$80),0) -> 1169666.8 | L11: =IF(AND($A11>=Inputs!$B$83,$A11<Inputs!$B$83+Inputs!$B$41),Inputs!$B$40*(1+Inputs!$B$8)^($A11-Inputs!$B$80),0) -> 0 | M11: =IF($A11>=Inputs!$B$81,Inputs!$B$32*(1+Inputs!$B$5)^($A11-Inputs!$B$80)*IF(AND(Inputs!$B$55=1,$A11>Inputs!$B$84),Inputs!$B$54,1),0) -> 0 | N11: =INDEX(Medical!$J$63:$J$109,MATCH($A11,Medical!$A$63:$A$109,0)) -> 0 | O11: =IF($A11>=Inputs!$B$81,Inputs!$B$39,0) -> 0 | P11: =IF(AND(Inputs!$B$58=1,$A11=Inputs!$B$57),Inputs!$B$56,0)+IF(AND(Inputs!$B$61=1,$A11>=Inputs!$B$60),Inputs!$B$59,0) -> 0 | Q11: =D11+E11-H11-I11+J11-K11-L11-M11-N11+O11+P11-IF($A11<Inputs!$B$81,Inputs!$B$42,0) -> 874611.56 | R11: =U10 -> 16481445 | S11: =R11*Inputs!$B$35 -> 791109.36 | T11: =IF($A11=Inputs!$B$81,-Inputs!$B$38,0) -> 0 | U11: =MAX(R11+S11+Q11+T11,0) -> 18147166
A12: 2034 | B12: =$A12-1972 -> 62 | C12: =$A12-1977 -> 57 | D12: =IF($A12<Inputs!$B$81,(Inputs!$B$27+Inputs!$B$28)*(1+Inputs!$B$6)^($A12-Inputs!$B$80),0) -> 1520124.1 | E12: =IF($A12<Inputs!$B$82,Inputs!$B$29*(1+Inputs!$B$7)^($A12-Inputs!$B$80),0) -> 912074.46 | F12: =(Inputs!$B$18+Inputs!$B$20+2*Inputs!$B$21)*(1+Inputs!$B$5)^($A12-Inputs!$B$80) -> 481269.14 | G12: =Inputs!$B$18*(1+Inputs!$B$5)^($A12-Inputs!$B$80) -> 176668.42 | H12: =IF(D12=0,0,IF(MAX(D12-Inputs!$B$22-Tax!$B$4/2-F12,0)>200000,Inputs!$B$24+(MAX(D12-Inputs!$B$22-Tax!$B$4/2-F12,0)-200000)*Inputs!$B$23,IF(MAX(D12-Inputs!$B$22-Tax!$B$4/2-F12,0)>150000,9000+(MAX(D12-Inputs!$B$22-Tax!$B$4/2-F12,0)-150000)*0.14,IF(MAX(D12-Inputs!$B$22-Tax!$B$4/2-F12,0)>100000,4000+(MAX(D12-Inputs!$B$22-Tax!$B$4/2-F12,0)-100000)*0.1,IF(MAX(D12-Inputs!$B$22-Tax!$B$4/2-F12,0)>50000,1000+(MAX(D12-Inputs!$B$22-Tax!$B$4/2-F12,0)-50000)*0.06,MAX(MAX(D12-Inputs!$B$22-Tax!$B$4/2-F12,0),0)*0.02))))) -> 150190.34 | I12: =IF(E12=0,0,IF(MAX(E12-Inputs!$B$22-Tax!$B$4/2-G12,0)>200000,Inputs!$B$24+(MAX(E12-Inputs!$B$22-Tax!$B$4/2-G12,0)-200000)*Inputs!$B$23,IF(MAX(E12-Inputs!$B$22-Tax!$B$4/2-G12,0)>150000,9000+(MAX(E12-Inputs!$B$22-Tax!$B$4/2-G12,0)-150000)*0.14,IF(MAX(E12-Inputs!$B$22-Tax!$B$4/2-G12,0)>100000,4000+(MAX(E12-Inputs!$B$22-Tax!$B$4/2-G12,0)-100000)*0.1,IF(MAX(E12-Inputs!$B$22-Tax!$B$4/2-G12,0)>50000,1000+(MAX(E12-Inputs!$B$22-Tax!$B$4/2-G12,0)-50000)*0.06,MAX(MAX(E12-Inputs!$B$22-Tax!$B$4/2-G12,0),0)*0.02))))) -> 98604.027 | J12: =IF(D12>0,Inputs!$B$22,0)+IF(E12>0,Inputs!$B$22,0) -> 36000 | K12: =IF($A12<Inputs!$B$81,Inputs!$B$31*(1+Inputs!$B$5)^($A12-Inputs!$B$80),0) -> 1198908.5 | L12: =IF(AND($A12>=Inputs!$B$83,$A12<Inputs!$B$83+Inputs!$B$41),Inputs!$B$40*(1+Inputs!$B$8)^($A12-Inputs!$B$80),0) -> 0 | M12: =IF($A12>=Inputs!$B$81,Inputs!$B$32*(1+Inputs!$B$5)^($A12-Inputs!$B$80)*IF(AND(Inputs!$B$55=1,$A12>Inputs!$B$84),Inputs!$B$54,1),0) -> 0 | N12: =INDEX(Medical!$J$63:$J$109,MATCH($A12,Medical!$A$63:$A$109,0)) -> 0 | O12: =IF($A12>=Inputs!$B$81,Inputs!$B$39,0) -> 0 | P12: =IF(AND(Inputs!$B$58=1,$A12=Inputs!$B$57),Inputs!$B$56,0)+IF(AND(Inputs!$B$61=1,$A12>=Inputs!$B$60),Inputs!$B$59,0) -> 0 | Q12: =D12+E12-H12-I12+J12-K12-L12-M12-N12+O12+P12-IF($A12<Inputs!$B$81,Inputs!$B$42,0) -> 906895.74 | R12: =U11 -> 18147166 | S12: =R12*Inputs!$B$35 -> 871063.96 | T12: =IF($A12=Inputs!$B$81,-Inputs!$B$38,0) -> 0 | U12: =MAX(R12+S12+Q12+T12,0) -> 19925126
A13: 2035 | B13: =$A13-1972 -> 63 | C13: =$A13-1977 -> 58 | D13: =IF($A13<Inputs!$B$81,(Inputs!$B$27+Inputs!$B$28)*(1+Inputs!$B$6)^($A13-Inputs!$B$80),0) -> 1565727.8 | E13: =IF($A13<Inputs!$B$82,Inputs!$B$29*(1+Inputs!$B$7)^($A13-Inputs!$B$80),0) -> 939436.69 | F13: =(Inputs!$B$18+Inputs!$B$20+2*Inputs!$B$21)*(1+Inputs!$B$5)^($A13-Inputs!$B$80) -> 493300.87 | G13: =Inputs!$B$18*(1+Inputs!$B$5)^($A13-Inputs!$B$80) -> 181085.13 | H13: =IF(D13=0,0,IF(MAX(D13-Inputs!$B$22-Tax!$B$4/2-F13,0)>200000,Inputs!$B$24+(MAX(D13-Inputs!$B$22-Tax!$B$4/2-F13,0)-200000)*Inputs!$B$23,IF(MAX(D13-Inputs!$B$22-Tax!$B$4/2-F13,0)>150000,9000+(MAX(D13-Inputs!$B$22-Tax!$B$4/2-F13,0)-150000)*0.14,IF(MAX(D13-Inputs!$B$22-Tax!$B$4/2-F13,0)>100000,4000+(MAX(D13-Inputs!$B$22-Tax!$B$4/2-F13,0)-100000)*0.1,IF(MAX(D13-Inputs!$B$22-Tax!$B$4/2-F13,0)>50000,1000+(MAX(D13-Inputs!$B$22-Tax!$B$4/2-F13,0)-50000)*0.06,MAX(MAX(D13-Inputs!$B$22-Tax!$B$4/2-F13,0),0)*0.02))))) -> 155897.58 | I13: =IF(E13=0,0,IF(MAX(E13-Inputs!$B$22-Tax!$B$4/2-G13,0)>200000,Inputs!$B$24+(MAX(E13-Inputs!$B$22-Tax!$B$4/2-G13,0)-200000)*Inputs!$B$23,IF(MAX(E13-Inputs!$B$22-Tax!$B$4/2-G13,0)>150000,9000+(MAX(E13-Inputs!$B$22-Tax!$B$4/2-G13,0)-150000)*0.14,IF(MAX(E13-Inputs!$B$22-Tax!$B$4/2-G13,0)>100000,4000+(MAX(E13-Inputs!$B$22-Tax!$B$4/2-G13,0)-100000)*0.1,IF(MAX(E13-Inputs!$B$22-Tax!$B$4/2-G13,0)>50000,1000+(MAX(E13-Inputs!$B$22-Tax!$B$4/2-G13,0)-50000)*0.06,MAX(MAX(E13-Inputs!$B$22-Tax!$B$4/2-G13,0),0)*0.02))))) -> 102504.77 | J13: =IF(D13>0,Inputs!$B$22,0)+IF(E13>0,Inputs!$B$22,0) -> 36000 | K13: =IF($A13<Inputs!$B$81,Inputs!$B$31*(1+Inputs!$B$5)^($A13-Inputs!$B$80),0) -> 1228881.2 | L13: =IF(AND($A13>=Inputs!$B$83,$A13<Inputs!$B$83+Inputs!$B$41),Inputs!$B$40*(1+Inputs!$B$8)^($A13-Inputs!$B$80),0) -> 0 | M13: =IF($A13>=Inputs!$B$81,Inputs!$B$32*(1+Inputs!$B$5)^($A13-Inputs!$B$80)*IF(AND(Inputs!$B$55=1,$A13>Inputs!$B$84),Inputs!$B$54,1),0) -> 0 | N13: =INDEX(Medical!$J$63:$J$109,MATCH($A13,Medical!$A$63:$A$109,0)) -> 0 | O13: =IF($A13>=Inputs!$B$81,Inputs!$B$39,0) -> 0 | P13: =IF(AND(Inputs!$B$58=1,$A13=Inputs!$B$57),Inputs!$B$56,0)+IF(AND(Inputs!$B$61=1,$A13>=Inputs!$B$60),Inputs!$B$59,0) -> 0 | Q13: =D13+E13-H13-I13+J13-K13-L13-M13-N13+O13+P13-IF($A13<Inputs!$B$81,Inputs!$B$42,0) -> 940281 | R13: =U12 -> 19925126 | S13: =R13*Inputs!$B$35 -> 956406.03 | T13: =IF($A13=Inputs!$B$81,-Inputs!$B$38,0) -> 0 | U13: =MAX(R13+S13+Q13+T13,0) -> 21821813
A14: 2036 | B14: =$A14-1972 -> 64 | C14: =$A14-1977 -> 59 | D14: =IF($A14<Inputs!$B$81,(Inputs!$B$27+Inputs!$B$28)*(1+Inputs!$B$6)^($A14-Inputs!$B$80),0) -> 1612699.7 | E14: =IF($A14<Inputs!$B$82,Inputs!$B$29*(1+Inputs!$B$7)^($A14-Inputs!$B$80),0) -> 967619.79 | F14: =(Inputs!$B$18+Inputs!$B$20+2*Inputs!$B$21)*(1+Inputs!$B$5)^($A14-Inputs!$B$80) -> 505633.39 | G14: =Inputs!$B$18*(1+Inputs!$B$5)^($A14-Inputs!$B$80) -> 185612.26 | H14: =IF(D14=0,0,IF(MAX(D14-Inputs!$B$22-Tax!$B$4/2-F14,0)>200000,Inputs!$B$24+(MAX(D14-Inputs!$B$22-Tax!$B$4/2-F14,0)-200000)*Inputs!$B$23,IF(MAX(D14-Inputs!$B$22-Tax!$B$4/2-F14,0)>150000,9000+(MAX(D14-Inputs!$B$22-Tax!$B$4/2-F14,0)-150000)*0.14,IF(MAX(D14-Inputs!$B$22-Tax!$B$4/2-F14,0)>100000,4000+(MAX(D14-Inputs!$B$22-Tax!$B$4/2-F14,0)-100000)*0.1,IF(MAX(D14-Inputs!$B$22-Tax!$B$4/2-F14,0)>50000,1000+(MAX(D14-Inputs!$B$22-Tax!$B$4/2-F14,0)-50000)*0.06,MAX(MAX(D14-Inputs!$B$22-Tax!$B$4/2-F14,0),0)*0.02))))) -> 161786.26 | I14: =IF(E14=0,0,IF(MAX(E14-Inputs!$B$22-Tax!$B$4/2-G14,0)>200000,Inputs!$B$24+(MAX(E14-Inputs!$B$22-Tax!$B$4/2-G14,0)-200000)*Inputs!$B$23,IF(MAX(E14-Inputs!$B$22-Tax!$B$4/2-G14,0)>150000,9000+(MAX(E14-Inputs!$B$22-Tax!$B$4/2-G14,0)-150000)*0.14,IF(MAX(E14-Inputs!$B$22-Tax!$B$4/2-G14,0)>100000,4000+(MAX(E14-Inputs!$B$22-Tax!$B$4/2-G14,0)-100000)*0.1,IF(MAX(E14-Inputs!$B$22-Tax!$B$4/2-G14,0)>50000,1000+(MAX(E14-Inputs!$B$22-Tax!$B$4/2-G14,0)-50000)*0.06,MAX(MAX(E14-Inputs!$B$22-Tax!$B$4/2-G14,0),0)*0.02))))) -> 106526.28 | J14: =IF(D14>0,Inputs!$B$22,0)+IF(E14>0,Inputs!$B$22,0) -> 36000 | K14: =IF($A14<Inputs!$B$81,Inputs!$B$31*(1+Inputs!$B$5)^($A14-Inputs!$B$80),0) -> 1259603.2 | L14: =IF(AND($A14>=Inputs!$B$83,$A14<Inputs!$B$83+Inputs!$B$41),Inputs!$B$40*(1+Inputs!$B$8)^($A14-Inputs!$B$80),0) -> 0 | M14: =IF($A14>=Inputs!$B$81,Inputs!$B$32*(1+Inputs!$B$5)^($A14-Inputs!$B$80)*IF(AND(Inputs!$B$55=1,$A14>Inputs!$B$84),Inputs!$B$54,1),0) -> 0 | N14: =INDEX(Medical!$J$63:$J$109,MATCH($A14,Medical!$A$63:$A$109,0)) -> 0 | O14: =IF($A14>=Inputs!$B$81,Inputs!$B$39,0) -> 0 | P14: =IF(AND(Inputs!$B$58=1,$A14=Inputs!$B$57),Inputs!$B$56,0)+IF(AND(Inputs!$B$61=1,$A14>=Inputs!$B$60),Inputs!$B$59,0) -> 0 | Q14: =D14+E14-H14-I14+J14-K14-L14-M14-N14+O14+P14-IF($A14<Inputs!$B$81,Inputs!$B$42,0) -> 974803.71 | R14: =U13 -> 21821813 | S14: =R14*Inputs!$B$35 -> 1047447 | T14: =IF($A14=Inputs!$B$81,-Inputs!$B$38,0) -> 0 | U14: =MAX(R14+S14+Q14+T14,0) -> 23844063
A15: 2037 | B15: =$A15-1972 -> 65 | C15: =$A15-1977 -> 60 | D15: =IF($A15<Inputs!$B$81,(Inputs!$B$27+Inputs!$B$28)*(1+Inputs!$B$6)^($A15-Inputs!$B$80),0) -> 0 | E15: =IF($A15<Inputs!$B$82,Inputs!$B$29*(1+Inputs!$B$7)^($A15-Inputs!$B$80),0) -> 996648.39 | F15: =(Inputs!$B$18+Inputs!$B$20+2*Inputs!$B$21)*(1+Inputs!$B$5)^($A15-Inputs!$B$80) -> 518274.23 | G15: =Inputs!$B$18*(1+Inputs!$B$5)^($A15-Inputs!$B$80) -> 190252.57 | H15: =IF(D15=0,0,IF(MAX(D15-Inputs!$B$22-Tax!$B$4/2-F15,0)>200000,Inputs!$B$24+(MAX(D15-Inputs!$B$22-Tax!$B$4/2-F15,0)-200000)*Inputs!$B$23,IF(MAX(D15-Inputs!$B$22-Tax!$B$4/2-F15,0)>150000,9000+(MAX(D15-Inputs!$B$22-Tax!$B$4/2-F15,0)-150000)*0.14,IF(MAX(D15-Inputs!$B$22-Tax!$B$4/2-F15,0)>100000,4000+(MAX(D15-Inputs!$B$22-Tax!$B$4/2-F15,0)-100000)*0.1,IF(MAX(D15-Inputs!$B$22-Tax!$B$4/2-F15,0)>50000,1000+(MAX(D15-Inputs!$B$22-Tax!$B$4/2-F15,0)-50000)*0.06,MAX(MAX(D15-Inputs!$B$22-Tax!$B$4/2-F15,0),0)*0.02))))) -> 0 | I15: =IF(E15=0,0,IF(MAX(E15-Inputs!$B$22-Tax!$B$4/2-G15,0)>200000,Inputs!$B$24+(MAX(E15-Inputs!$B$22-Tax!$B$4/2-G15,0)-200000)*Inputs!$B$23,IF(MAX(E15-Inputs!$B$22-Tax!$B$4/2-G15,0)>150000,9000+(MAX(E15-Inputs!$B$22-Tax!$B$4/2-G15,0)-150000)*0.14,IF(MAX(E15-Inputs!$B$22-Tax!$B$4/2-G15,0)>100000,4000+(MAX(E15-Inputs!$B$22-Tax!$B$4/2-G15,0)-100000)*0.1,IF(MAX(E15-Inputs!$B$22-Tax!$B$4/2-G15,0)>50000,1000+(MAX(E15-Inputs!$B$22-Tax!$B$4/2-G15,0)-50000)*0.06,MAX(MAX(E15-Inputs!$B$22-Tax!$B$4/2-G15,0),0)*0.02))))) -> 110672.29 | J15: =IF(D15>0,Inputs!$B$22,0)+IF(E15>0,Inputs!$B$22,0) -> 18000 | K15: =IF($A15<Inputs!$B$81,Inputs!$B$31*(1+Inputs!$B$5)^($A15-Inputs!$B$80),0) -> 0 | L15: =IF(AND($A15>=Inputs!$B$83,$A15<Inputs!$B$83+Inputs!$B$41),Inputs!$B$40*(1+Inputs!$B$8)^($A15-Inputs!$B$80),0) -> 0 | M15: =IF($A15>=Inputs!$B$81,Inputs!$B$32*(1+Inputs!$B$5)^($A15-Inputs!$B$80)*IF(AND(Inputs!$B$55=1,$A15>Inputs!$B$84),Inputs!$B$54,1),0) -> 1023427.6 | N15: =INDEX(Medical!$J$63:$J$109,MATCH($A15,Medical!$A$63:$A$109,0)) -> 0 | O15: =IF($A15>=Inputs!$B$81,Inputs!$B$39,0) -> 268000 | P15: =IF(AND(Inputs!$B$58=1,$A15=Inputs!$B$57),Inputs!$B$56,0)+IF(AND(Inputs!$B$61=1,$A15>=Inputs!$B$60),Inputs!$B$59,0) -> 0 | Q15: =D15+E15-H15-I15+J15-K15-L15-M15-N15+O15+P15-IF($A15<Inputs!$B$81,Inputs!$B$42,0) -> 148548.5 | R15: =U14 -> 23844063 | S15: =R15*Inputs!$B$35 -> 1144515 | T15: =IF($A15=Inputs!$B$81,-Inputs!$B$38,0) -> -4120000 | U15: =MAX(R15+S15+Q15+T15,0) -> 21017127
A16: 2038 | B16: =$A16-1972 -> 66 | C16: =$A16-1977 -> 61 | D16: =IF($A16<Inputs!$B$81,(Inputs!$B$27+Inputs!$B$28)*(1+Inputs!$B$6)^($A16-Inputs!$B$80),0) -> 0 | E16: =IF($A16<Inputs!$B$82,Inputs!$B$29*(1+Inputs!$B$7)^($A16-Inputs!$B$80),0) -> 1026547.8 | F16: =(Inputs!$B$18+Inputs!$B$20+2*Inputs!$B$21)*(1+Inputs!$B$5)^($A16-Inputs!$B$80) -> 531231.09 | G16: =Inputs!$B$18*(1+Inputs!$B$5)^($A16-Inputs!$B$80) -> 195008.88 | H16: =IF(D16=0,0,IF(MAX(D16-Inputs!$B$22-Tax!$B$4/2-F16,0)>200000,Inputs!$B$24+(MAX(D16-Inputs!$B$22-Tax!$B$4/2-F16,0)-200000)*Inputs!$B$23,IF(MAX(D16-Inputs!$B$22-Tax!$B$4/2-F16,0)>150000,9000+(MAX(D16-Inputs!$B$22-Tax!$B$4/2-F16,0)-150000)*0.14,IF(MAX(D16-Inputs!$B$22-Tax!$B$4/2-F16,0)>100000,4000+(MAX(D16-Inputs!$B$22-Tax!$B$4/2-F16,0)-100000)*0.1,IF(MAX(D16-Inputs!$B$22-Tax!$B$4/2-F16,0)>50000,1000+(MAX(D16-Inputs!$B$22-Tax!$B$4/2-F16,0)-50000)*0.06,MAX(MAX(D16-Inputs!$B$22-Tax!$B$4/2-F16,0),0)*0.02))))) -> 0 | I16: =IF(E16=0,0,IF(MAX(E16-Inputs!$B$22-Tax!$B$4/2-G16,0)>200000,Inputs!$B$24+(MAX(E16-Inputs!$B$22-Tax!$B$4/2-G16,0)-200000)*Inputs!$B$23,IF(MAX(E16-Inputs!$B$22-Tax!$B$4/2-G16,0)>150000,9000+(MAX(E16-Inputs!$B$22-Tax!$B$4/2-G16,0)-150000)*0.14,IF(MAX(E16-Inputs!$B$22-Tax!$B$4/2-G16,0)>100000,4000+(MAX(E16-Inputs!$B$22-Tax!$B$4/2-G16,0)-100000)*0.1,IF(MAX(E16-Inputs!$B$22-Tax!$B$4/2-G16,0)>50000,1000+(MAX(E16-Inputs!$B$22-Tax!$B$4/2-G16,0)-50000)*0.06,MAX(MAX(E16-Inputs!$B$22-Tax!$B$4/2-G16,0),0)*0.02))))) -> 114946.62 | J16: =IF(D16>0,Inputs!$B$22,0)+IF(E16>0,Inputs!$B$22,0) -> 18000 | K16: =IF($A16<Inputs!$B$81,Inputs!$B$31*(1+Inputs!$B$5)^($A16-Inputs!$B$80),0) -> 0 | L16: =IF(AND($A16>=Inputs!$B$83,$A16<Inputs!$B$83+Inputs!$B$41),Inputs!$B$40*(1+Inputs!$B$8)^($A16-Inputs!$B$80),0) -> 0 | M16: =IF($A16>=Inputs!$B$81,Inputs!$B$32*(1+Inputs!$B$5)^($A16-Inputs!$B$80)*IF(AND(Inputs!$B$55=1,$A16>Inputs!$B$84),Inputs!$B$54,1),0) -> 1049013.3 | N16: =INDEX(Medical!$J$63:$J$109,MATCH($A16,Medical!$A$63:$A$109,0)) -> 0 | O16: =IF($A16>=Inputs!$B$81,Inputs!$B$39,0) -> 268000 | P16: =IF(AND(Inputs!$B$58=1,$A16=Inputs!$B$57),Inputs!$B$56,0)+IF(AND(Inputs!$B$61=1,$A16>=Inputs!$B$60),Inputs!$B$59,0) -> 0 | Q16: =D16+E16-H16-I16+J16-K16-L16-M16-N16+O16+P16-IF($A16<Inputs!$B$81,Inputs!$B$42,0) -> 148587.93 | R16: =U15 -> 21017127 | S16: =R16*Inputs!$B$35 -> 1008822.1 | T16: =IF($A16=Inputs!$B$81,-Inputs!$B$38,0) -> 0 | U16: =MAX(R16+S16+Q16+T16,0) -> 22174537
... A50: 2072 | B50: =$A50-1972 -> 100 | C50: =$A50-1977 -> 95 | D50: =IF($A50<Inputs!$B$81,(Inputs!$B$27+Inputs!$B$28)*(1+Inputs!$B$6)^($A50-Inputs!$B$80),0) -> 0 | E50: =IF($A50<Inputs!$B$82,Inputs!$B$29*(1+Inputs!$B$7)^($A50-Inputs!$B$80),0) -> 0 | F50: =(Inputs!$B$18+Inputs!$B$20+2*Inputs!$B$21)*(1+Inputs!$B$5)^($A50-Inputs!$B$80) -> 1229971.1 | G50: =Inputs!$B$18*(1+Inputs!$B$5)^($A50-Inputs!$B$80) -> 451508.37 | H50: =IF(D50=0,0,IF(MAX(D50-Inputs!$B$22-Tax!$B$4/2-F50,0)>200000,Inputs!$B$24+(MAX(D50-Inputs!$B$22-Tax!$B$4/2-F50,0)-200000)*Inputs!$B$23,IF(MAX(D50-Inputs!$B$22-Tax!$B$4/2-F50,0)>150000,9000+(MAX(D50-Inputs!$B$22-Tax!$B$4/2-F50,0)-150000)*0.14,IF(MAX(D50-Inputs!$B$22-Tax!$B$4/2-F50,0)>100000,4000+(MAX(D50-Inputs!$B$22-Tax!$B$4/2-F50,0)-100000)*0.1,IF(MAX(D50-Inputs!$B$22-Tax!$B$4/2-F50,0)>50000,1000+(MAX(D50-Inputs!$B$22-Tax!$B$4/2-F50,0)-50000)*0.06,MAX(MAX(D50-Inputs!$B$22-Tax!$B$4/2-F50,0),0)*0.02))))) -> 0 | I50: =IF(E50=0,0,IF(MAX(E50-Inputs!$B$22-Tax!$B$4/2-G50,0)>200000,Inputs!$B$24+(MAX(E50-Inputs!$B$22-Tax!$B$4/2-G50,0)-200000)*Inputs!$B$23,IF(MAX(E50-Inputs!$B$22-Tax!$B$4/2-G50,0)>150000,9000+(MAX(E50-Inputs!$B$22-Tax!$B$4/2-G50,0)-150000)*0.14,IF(MAX(E50-Inputs!$B$22-Tax!$B$4/2-G50,0)>100000,4000+(MAX(E50-Inputs!$B$22-Tax!$B$4/2-G50,0)-100000)*0.1,IF(MAX(E50-Inputs!$B$22-Tax!$B$4/2-G50,0)>50000,1000+(MAX(E50-Inputs!$B$22-Tax!$B$4/2-G50,0)-50000)*0.06,MAX(MAX(E50-Inputs!$B$22-Tax!$B$4/2-G50,0),0)*0.02))))) -> 0 | J50: =IF(D50>0,Inputs!$B$22,0)+IF(E50>0,Inputs!$B$22,0) -> 0 | K50: =IF($A50<Inputs!$B$81,Inputs!$B$31*(1+Inputs!$B$5)^($A50-Inputs!$B$80),0) -> 0 | L50: =IF(AND($A50>=Inputs!$B$83,$A50<Inputs!$B$83+Inputs!$B$41),Inputs!$B$40*(1+Inputs!$B$8)^($A50-Inputs!$B$80),0) -> 0 | M50: =IF($A50>=Inputs!$B$81,Inputs!$B$32*(1+Inputs!$B$5)^($A50-Inputs!$B$80)*IF(AND(Inputs!$B$55=1,$A50>Inputs!$B$84),Inputs!$B$54,1),0) -> 2428803.7 | N50: =INDEX(Medical!$J$63:$J$109,MATCH($A50,Medical!$A$63:$A$109,0)) -> 1607225.2 | O50: =IF($A50>=Inputs!$B$81,Inputs!$B$39,0) -> 268000 | P50: =IF(AND(Inputs!$B$58=1,$A50=Inputs!$B$57),Inputs!$B$56,0)+IF(AND(Inputs!$B$61=1,$A50>=Inputs!$B$60),Inputs!$B$59,0) -> 0 | Q50: =D50+E50-H50-I50+J50-K50-L50-M50-N50+O50+P50-IF($A50<Inputs!$B$81,Inputs!$B$42,0) -> -3768028.8 | R50: =U49 -> 0 | S50: =R50*Inputs!$B$35 -> 0 | T50: =IF($A50=Inputs!$B$81,-Inputs!$B$38,0) -> 0 | U50: =MAX(R50+S50+Q50+T50,0) -> 0

Sheet Outputs
A1: OUTPUTS — the only numbers that go in the proposal
A2: Green = pulled from another tab. Quote these, not your own arithmetic.
A4: POSITION TODAY
A5: Net worth | B5: =BalanceSheet!B33 -> 24405000
A6: Parents' investable pool | B6: =BalanceSheet!$B$37 -> 9790000
A7: Annual surplus (after tax, MPF, premiums) | B7: =Tax!B27-Inputs!$B$42 -> 604630
A8: Emergency reserve, months | B8: =BalanceSheet!B7/(Inputs!$B$31/12) -> 30.487805
A9: TAX
A10: Couple — separate assessment | B10: =Tax!B15 -> 181770
A11: Couple — joint assessment | B11: =Tax!B16 -> 199770
A12: Saving from separate | B12: =Tax!B17 -> 18000
A13: PROJECTION (deterministic, plan return; backstops only if switched on)
A14: Portfolio at Adrian's retirement (2037, nominal) | B14: =INDEX(Projection!U:U,MATCH(Inputs!$B$81,Projection!A:A,0)) -> 21017127
A15: Portfolio at Carmen 89 (2066) | B15: =INDEX(Projection!U:U,MATCH(Inputs!$B$85,Projection!A:A,0)) -> 0
A16: Portfolio at Carmen 95 (2072) | B16: =INDEX(Projection!U:U,MATCH(Inputs!$B$86,Projection!A:A,0)) -> 0
A17: Portfolio at 2037 in TODAY money | B17: =INDEX(Projection!U:U,MATCH(Inputs!$B$81,Projection!A:A,0))/(1+Inputs!$B$5)^(Inputs!$B$81-Inputs!$B$80) -> 16018094
A18: Retirement need at 2037 (today money) | B18: =Inputs!$B$32*(1-(1+0.02)^-29)/0.02 -> 17038620
A19: First year the portfolio runs out (0 = lasts to 2072) | B19: =IFERROR(INDEX(Projection!A4:A50,MATCH(0,Projection!U4:U50,0)),0) -> 2066
A20: Carmen's age that year | B20: =IF(B19=0,"lasts",B19-1977) -> 89
A21: Money lasts to 89? (deterministic) | B21: =IF(INDEX(Projection!U:U,MATCH(Inputs!$B$85,Projection!A:A,0))>0,"YES","NO") -> NO
A22: Money lasts to 95? (deterministic) | B22: =IF(INDEX(Projection!U:U,MATCH(Inputs!$B$86,Projection!A:A,0))>0,"YES","NO") -> NO
A23: EDUCATION AND MEDICAL
A24: Total education cost (nominal) | B24: =SUM(Projection!L4:L50) -> 2851147.7
A25: Medical line at 2037 (nominal) | B25: =INDEX(Projection!N:N,MATCH(Inputs!$B$81,Projection!A:A,0)) -> 0
A26: Medical line at Carmen 89 (nominal) | B26: =INDEX(Projection!N:N,MATCH(Inputs!$B$85,Projection!A:A,0)) -> 872123.38
A27: Medical line to Carmen 89, total (nominal) | B27: =SUMPRODUCT((Projection!A4:A50<=Inputs!$B$85)*Projection!N4:N50) -> 11842102
